{"definitions" : [{"name" : {"id" : "println1", "type" : {"op" : "Function", "params" : [{"op" : "String"}], "return" : {"op" : "Unit"}, "purity" : "Effectful"}},
"value" : {"op" : "Abs",
"params" : [{"id" : "value2", "type" : {"op" : "String"}}],
"body" : {"op" : "Primitive",
"name" : "println(String): Unit",
"args" : [{"op" : "Var", "id" : "value2", "type" : {"op" : "String"}}],
"returns" : [{"id" : "v_tmp_52625292", "type" : {"op" : "Unit"}}],
"rest" : {"op" : "Var", "id" : "v_tmp_52625292", "type" : {"op" : "Unit"}}}},
"export_as" : ["println"]},
{"name" : {"id" : "show14", "type" : {"op" : "Function", "params" : [{"op" : "Int"}], "return" : {"op" : "String"}, "purity" : "Pure"}},
"value" : {"op" : "Abs",
"params" : [{"id" : "value13", "type" : {"op" : "Int"}}],
"body" : {"op" : "Primitive",
"name" : "show(Int): String",
"args" : [{"op" : "Var", "id" : "value13", "type" : {"op" : "Int"}}],
"returns" : [{"id" : "v_tmp_52635293", "type" : {"op" : "String"}}],
"rest" : {"op" : "Var", "id" : "v_tmp_52635293", "type" : {"op" : "String"}}}},
"export_as" : ["show"]},
{"name" : {"id" : "infixConcat35", "type" : {"op" : "Function", "params" : [{"op" : "String"},
{"op" : "String"}], "return" : {"op" : "String"}, "purity" : "Pure"}},
"value" : {"op" : "Abs",
"params" : [{"id" : "s133", "type" : {"op" : "String"}}, {"id" : "s234", "type" : {"op" : "String"}}],
"body" : {"op" : "Primitive",
"name" : "infixConcat(String, String): String",
"args" : [{"op" : "Var", "id" : "s133", "type" : {"op" : "String"}}, {"op" : "Var", "id" : "s234", "type" : {"op" : "String"}}],
"returns" : [{"id" : "v_tmp_52645294", "type" : {"op" : "String"}}],
"rest" : {"op" : "Var", "id" : "v_tmp_52645294", "type" : {"op" : "String"}}}},
"export_as" : ["infixConcat"]},
{"name" : {"id" : "length37", "type" : {"op" : "Function", "params" : [{"op" : "String"}], "return" : {"op" : "Int"}, "purity" : "Pure"}},
"value" : {"op" : "Abs",
"params" : [{"id" : "str36", "type" : {"op" : "String"}}],
"body" : {"op" : "Primitive",
"name" : "length(String): Int",
"args" : [{"op" : "Var", "id" : "str36", "type" : {"op" : "String"}}],
"returns" : [{"id" : "v_tmp_52655295", "type" : {"op" : "Int"}}],
"rest" : {"op" : "Var", "id" : "v_tmp_52655295", "type" : {"op" : "Int"}}}},
"export_as" : ["length"]},
{"name" : {"id" : "infixEq72", "type" : {"op" : "Function", "params" : [{"op" : "Int"},
{"op" : "Int"}], "return" : {"op" : "Bool"}, "purity" : "Pure"}},
"value" : {"op" : "Abs",
"params" : [{"id" : "x70", "type" : {"op" : "Int"}}, {"id" : "y71", "type" : {"op" : "Int"}}],
"body" : {"op" : "Primitive",
"name" : "infixEq(Int, Int): Boolean",
"args" : [{"op" : "Var", "id" : "x70", "type" : {"op" : "Int"}}, {"op" : "Var", "id" : "y71", "type" : {"op" : "Int"}}],
"returns" : [{"id" : "v_tmp_52665296", "type" : {"op" : "Bool"}}],
"rest" : {"op" : "Var", "id" : "v_tmp_52665296", "type" : {"op" : "Bool"}}}},
"export_as" : ["infixEq"]},
{"name" : {"id" : "infixEq78", "type" : {"op" : "Function", "params" : [{"op" : "String"},
{"op" : "String"}], "return" : {"op" : "Bool"}, "purity" : "Pure"}},
"value" : {"op" : "Abs",
"params" : [{"id" : "x76", "type" : {"op" : "String"}}, {"id" : "y77", "type" : {"op" : "String"}}],
"body" : {"op" : "Primitive",
"name" : "infixEq(String, String): Boolean",
"args" : [{"op" : "Var", "id" : "x76", "type" : {"op" : "String"}}, {"op" : "Var", "id" : "y77", "type" : {"op" : "String"}}],
"returns" : [{"id" : "v_tmp_52675297", "type" : {"op" : "Bool"}}],
"rest" : {"op" : "Var", "id" : "v_tmp_52675297", "type" : {"op" : "Bool"}}}},
"export_as" : ["infixEq"]},
{"name" : {"id" : "infixAdd96", "type" : {"op" : "Function", "params" : [{"op" : "Int"},
{"op" : "Int"}], "return" : {"op" : "Int"}, "purity" : "Pure"}},
"value" : {"op" : "Abs",
"params" : [{"id" : "x94", "type" : {"op" : "Int"}}, {"id" : "y95", "type" : {"op" : "Int"}}],
"body" : {"op" : "Primitive",
"name" : "infixAdd(Int, Int): Int",
"args" : [{"op" : "Var", "id" : "x94", "type" : {"op" : "Int"}}, {"op" : "Var", "id" : "y95", "type" : {"op" : "Int"}}],
"returns" : [{"id" : "v_tmp_52685298", "type" : {"op" : "Int"}}],
"rest" : {"op" : "Var", "id" : "v_tmp_52685298", "type" : {"op" : "Int"}}}},
"export_as" : ["infixAdd"]},
{"name" : {"id" : "infixMul99", "type" : {"op" : "Function", "params" : [{"op" : "Int"},
{"op" : "Int"}], "return" : {"op" : "Int"}, "purity" : "Pure"}},
"value" : {"op" : "Abs",
"params" : [{"id" : "x97", "type" : {"op" : "Int"}}, {"id" : "y98", "type" : {"op" : "Int"}}],
"body" : {"op" : "Primitive",
"name" : "infixMul(Int, Int): Int",
"args" : [{"op" : "Var", "id" : "x97", "type" : {"op" : "Int"}}, {"op" : "Var", "id" : "y98", "type" : {"op" : "Int"}}],
"returns" : [{"id" : "v_tmp_52695299", "type" : {"op" : "Int"}}],
"rest" : {"op" : "Var", "id" : "v_tmp_52695299", "type" : {"op" : "Int"}}}},
"export_as" : ["infixMul"]},
{"name" : {"id" : "infixSub105", "type" : {"op" : "Function", "params" : [{"op" : "Int"},
{"op" : "Int"}], "return" : {"op" : "Int"}, "purity" : "Pure"}},
"value" : {"op" : "Abs",
"params" : [{"id" : "x103", "type" : {"op" : "Int"}}, {"id" : "y104", "type" : {"op" : "Int"}}],
"body" : {"op" : "Primitive",
"name" : "infixSub(Int, Int): Int",
"args" : [{"op" : "Var", "id" : "x103", "type" : {"op" : "Int"}}, {"op" : "Var", "id" : "y104", "type" : {"op" : "Int"}}],
"returns" : [{"id" : "v_tmp_52705300", "type" : {"op" : "Int"}}],
"rest" : {"op" : "Var", "id" : "v_tmp_52705300", "type" : {"op" : "Int"}}}},
"export_as" : ["infixSub"]},
{"name" : {"id" : "infixLt178", "type" : {"op" : "Function", "params" : [{"op" : "Int"},
{"op" : "Int"}], "return" : {"op" : "Bool"}, "purity" : "Pure"}},
"value" : {"op" : "Abs",
"params" : [{"id" : "x176", "type" : {"op" : "Int"}}, {"id" : "y177", "type" : {"op" : "Int"}}],
"body" : {"op" : "Primitive",
"name" : "infixLt(Int, Int): Boolean",
"args" : [{"op" : "Var", "id" : "x176", "type" : {"op" : "Int"}}, {"op" : "Var", "id" : "y177", "type" : {"op" : "Int"}}],
"returns" : [{"id" : "v_tmp_52715301", "type" : {"op" : "Bool"}}],
"rest" : {"op" : "Var", "id" : "v_tmp_52715301", "type" : {"op" : "Bool"}}}},
"export_as" : ["infixLt"]},
{"name" : {"id" : "infixGt184", "type" : {"op" : "Function", "params" : [{"op" : "Int"},
{"op" : "Int"}], "return" : {"op" : "Bool"}, "purity" : "Pure"}},
"value" : {"op" : "Abs",
"params" : [{"id" : "x182", "type" : {"op" : "Int"}}, {"id" : "y183", "type" : {"op" : "Int"}}],
"body" : {"op" : "Primitive",
"name" : "infixGt(Int, Int): Boolean",
"args" : [{"op" : "Var", "id" : "x182", "type" : {"op" : "Int"}}, {"op" : "Var", "id" : "y183", "type" : {"op" : "Int"}}],
"returns" : [{"id" : "v_tmp_52725302", "type" : {"op" : "Bool"}}],
"rest" : {"op" : "Var", "id" : "v_tmp_52725302", "type" : {"op" : "Bool"}}}},
"export_as" : ["infixGt"]},
{"name" : {"id" : "infixGte187", "type" : {"op" : "Function", "params" : [{"op" : "Int"},
{"op" : "Int"}], "return" : {"op" : "Bool"}, "purity" : "Pure"}},
"value" : {"op" : "Abs",
"params" : [{"id" : "x185", "type" : {"op" : "Int"}}, {"id" : "y186", "type" : {"op" : "Int"}}],
"body" : {"op" : "Primitive",
"name" : "infixGte(Int, Int): Boolean",
"args" : [{"op" : "Var", "id" : "x185", "type" : {"op" : "Int"}}, {"op" : "Var", "id" : "y186", "type" : {"op" : "Int"}}],
"returns" : [{"id" : "v_tmp_52735303", "type" : {"op" : "Bool"}}],
"rest" : {"op" : "Var", "id" : "v_tmp_52735303", "type" : {"op" : "Bool"}}}},
"export_as" : ["infixGte"]},
{"name" : {"id" : "toInt2452", "type" : {"op" : "Function", "params" : [{"op" : "String"}], "return" : {"op" : "Int"}, "purity" : "Pure"}},
"value" : {"op" : "Abs",
"params" : [{"id" : "ch2451", "type" : {"op" : "String"}}],
"body" : {"op" : "Primitive",
"name" : "charCode(String): Int",
"args" : [{"op" : "Var", "id" : "ch2451", "type" : {"op" : "String"}}],
"returns" : [{"id" : "v_tmp_52745304", "type" : {"op" : "Int"}}],
"rest" : {"op" : "Var", "id" : "v_tmp_52745304", "type" : {"op" : "Int"}}}},
"export_as" : ["toInt"]},
{"name" : {"id" : "infixLte2460", "type" : {"op" : "Function", "params" : [{"op" : "String"},
{"op" : "String"}], "return" : {"op" : "Bool"}, "purity" : "Pure"}},
"value" : {"op" : "Abs",
"params" : [{"id" : "x2458", "type" : {"op" : "String"}}, {"id" : "y2459", "type" : {"op" : "String"}}],
"body" : {"op" : "Primitive",
"name" : "infixLte(String, String): Boolean",
"args" : [{"op" : "Var", "id" : "x2458", "type" : {"op" : "String"}}, {"op" : "Var", "id" : "y2459", "type" : {"op" : "String"}}],
"returns" : [{"id" : "v_tmp_52755305", "type" : {"op" : "Bool"}}],
"rest" : {"op" : "Var", "id" : "v_tmp_52755305", "type" : {"op" : "Bool"}}}},
"export_as" : ["infixLte"]},
{"name" : {"id" : "infixGte2466", "type" : {"op" : "Function", "params" : [{"op" : "String"},
{"op" : "String"}], "return" : {"op" : "Bool"}, "purity" : "Pure"}},
"value" : {"op" : "Abs",
"params" : [{"id" : "x2464", "type" : {"op" : "String"}}, {"id" : "y2465", "type" : {"op" : "String"}}],
"body" : {"op" : "Primitive",
"name" : "infixGte(String, String): Boolean",
"args" : [{"op" : "Var", "id" : "x2464", "type" : {"op" : "String"}}, {"op" : "Var", "id" : "y2465", "type" : {"op" : "String"}}],
"returns" : [{"id" : "v_tmp_52765306", "type" : {"op" : "Bool"}}],
"rest" : {"op" : "Var", "id" : "v_tmp_52765306", "type" : {"op" : "Bool"}}}},
"export_as" : ["infixGte"]},
{"name" : {"id" : "unsafeCharAt2478", "type" : {"op" : "Function", "params" : [{"op" : "String"},
{"op" : "Int"}], "return" : {"op" : "String"}, "purity" : "Pure"}},
"value" : {"op" : "Abs",
"params" : [{"id" : "str2476", "type" : {"op" : "String"}}, {"id" : "n2477", "type" : {"op" : "Int"}}],
"body" : {"op" : "Primitive",
"name" : "!sexp:(\"charAt(Int, String): String\" $arg1:int $arg0:str)",
"args" : [{"op" : "Var", "id" : "str2476", "type" : {"op" : "String"}}, {"op" : "Var", "id" : "n2477", "type" : {"op" : "Int"}}],
"returns" : [{"id" : "v_tmp_52775307", "type" : {"op" : "String"}}],
"rest" : {"op" : "Var", "id" : "v_tmp_52775307", "type" : {"op" : "String"}}}},
"export_as" : ["unsafeCharAt"]},
{"name" : {"id" : "argCount2767", "type" : {"op" : "Function", "params" : [], "return" : {"op" : "Int"}, "purity" : "Effectful"}},
"value" : {"op" : "Abs",
"params" : [],
"body" : {"op" : "Primitive",
"name" : "get_argc(): Int",
"args" : [],
"returns" : [{"id" : "v_tmp_52785308", "type" : {"op" : "Int"}}],
"rest" : {"op" : "Var", "id" : "v_tmp_52785308", "type" : {"op" : "Int"}}}},
"export_as" : ["argCount"]},
{"name" : {"id" : "argument2769", "type" : {"op" : "Function", "params" : [{"op" : "Int"}], "return" : {"op" : "String"}, "purity" : "Effectful"}},
"value" : {"op" : "Abs",
"params" : [{"id" : "i2768", "type" : {"op" : "Int"}}],
"body" : {"op" : "Primitive",
"name" : "get_arg(Int): String",
"args" : [{"op" : "Var", "id" : "i2768", "type" : {"op" : "Int"}}],
"returns" : [{"id" : "v_tmp_52795309", "type" : {"op" : "String"}}],
"rest" : {"op" : "Var", "id" : "v_tmp_52795309", "type" : {"op" : "String"}}}},
"export_as" : ["argument"]},
{"name" : {"id" : "charAt2475", "type" : {"op" : "Function", "params" : [{"op" : "String"},
{"op" : "Int"},
{"op" : "Codata", "interface_tag" : "Exception532", "methods" : [{"tag" : "raise602", "params" : [{"op" : "Top"}, {"op" : "String"}], "return" : {"op" : "Bottom"}}]}], "return" : {"op" : "String"}, "purity" : "Effectful"}},
"value" : {"op" : "Abs",
"params" : [{"id" : "str2473", "type" : {"op" : "String"}}, {"id" : "index2474", "type" : {"op" : "Int"}}, {"id" : "Exception2728", "type" : {"op" : "Codata", "interface_tag" : "Exception532", "methods" : [{"tag" : "raise602", "params" : [{"op" : "Top"}, {"op" : "String"}], "return" : {"op" : "Bottom"}}]}}],
"body" : {"op" : "Let",
"definitions" : [{"name" : {"id" : "tmp5259", "type" : {"op" : "Bool"}},
"value" : {"op" : "App", "fn" : {"op" : "Var", "id" : "infixLt178", "type" : {"op" : "Function", "params" : [{"op" : "Int"},
{"op" : "Int"}], "return" : {"op" : "Bool"}, "purity" : "Effectful"}}, "args" : [{"op" : "Var", "id" : "index2474", "type" : {"op" : "Int"}}, {"op" : "Literal", "type" : {"op" : "Int"}, "value" : 0}]},
"export_as" : ["tmp"]}],
"body" : {"op" : "Let",
"definitions" : [{"name" : {"id" : "v_r_31693998", "type" : {"op" : "Bool"}},
"value" : {"op" : "IfZero",
"cond" : {"op" : "Var", "id" : "tmp5259", "type" : {"op" : "Bool"}},
"then" : {"op" : "Let",
"definitions" : [{"name" : {"id" : "tmp5221", "type" : {"op" : "Int"}},
"value" : {"op" : "App", "fn" : {"op" : "Var", "id" : "length37", "type" : {"op" : "Function", "params" : [{"op" : "String"}], "return" : {"op" : "Int"}, "purity" : "Effectful"}}, "args" : [{"op" : "Var", "id" : "str2473", "type" : {"op" : "String"}}]},
"export_as" : ["tmp"]}],
"body" : {"op" : "Let",
"definitions" : [{"name" : {"id" : "tmp5222", "type" : {"op" : "Bool"}},
"value" : {"op" : "App", "fn" : {"op" : "Var", "id" : "infixGte187", "type" : {"op" : "Function", "params" : [{"op" : "Int"},
{"op" : "Int"}], "return" : {"op" : "Bool"}, "purity" : "Effectful"}}, "args" : [{"op" : "Var", "id" : "index2474", "type" : {"op" : "Int"}}, {"op" : "Var", "id" : "tmp5221", "type" : {"op" : "Int"}}]},
"export_as" : ["tmp"]}],
"body" : {"op" : "Var", "id" : "tmp5222", "type" : {"op" : "Bool"}}}},
"else" : {"op" : "Literal", "type" : {"op" : "Bool"}, "value" : true}},
"export_as" : ["v_r_3169"]}],
"body" : {"op" : "IfZero",
"cond" : {"op" : "Var", "id" : "v_r_31693998", "type" : {"op" : "Bool"}},
"then" : {"op" : "Let",
"definitions" : [{"name" : {"id" : "tmp5229", "type" : {"op" : "String"}},
"value" : {"op" : "App", "fn" : {"op" : "Var", "id" : "unsafeCharAt2478", "type" : {"op" : "Function", "params" : [{"op" : "String"},
{"op" : "Int"}], "return" : {"op" : "String"}, "purity" : "Effectful"}}, "args" : [{"op" : "Var", "id" : "str2473", "type" : {"op" : "String"}}, {"op" : "Var", "id" : "index2474", "type" : {"op" : "Int"}}]},
"export_as" : ["tmp"]}],
"body" : {"op" : "Var", "id" : "tmp5229", "type" : {"op" : "String"}}},
"else" : {"op" : "Let",
"definitions" : [{"name" : {"id" : "tmp5223", "type" : {"op" : "Data", "type_tag" : "OutOfBounds541", "constructors" : [{"tag" : "OutOfBounds604", "fields" : []}]}},
"value" : {"op" : "The",
"type" : {"op" : "Data", "type_tag" : "OutOfBounds541", "constructors" : [{"tag" : "OutOfBounds604", "fields" : []}]},
"term" : {"op" : "Construct", "type_tag" : "OutOfBounds541", "tag" : "OutOfBounds604", "args" : []}},
"export_as" : ["tmp"]}],
"body" : {"op" : "Let",
"definitions" : [{"name" : {"id" : "tmp5224", "type" : {"op" : "String"}},
"value" : {"op" : "App", "fn" : {"op" : "Var", "id" : "show14", "type" : {"op" : "Function", "params" : [{"op" : "Int"}], "return" : {"op" : "String"}, "purity" : "Effectful"}}, "args" : [{"op" : "Var", "id" : "index2474", "type" : {"op" : "Int"}}]},
"export_as" : ["tmp"]}],
"body" : {"op" : "Let",
"definitions" : [{"name" : {"id" : "tmp5225", "type" : {"op" : "String"}},
"value" : {"op" : "App", "fn" : {"op" : "Var", "id" : "infixConcat35", "type" : {"op" : "Function", "params" : [{"op" : "String"},
{"op" : "String"}], "return" : {"op" : "String"}, "purity" : "Effectful"}}, "args" : [{"op" : "Literal", "type" : {"op" : "String"}, "value" : "Index out of bounds: "}, {"op" : "Var", "id" : "tmp5224", "type" : {"op" : "String"}}]},
"export_as" : ["tmp"]}],
"body" : {"op" : "Let",
"definitions" : [{"name" : {"id" : "tmp5226", "type" : {"op" : "String"}},
"value" : {"op" : "App", "fn" : {"op" : "Var", "id" : "infixConcat35", "type" : {"op" : "Function", "params" : [{"op" : "String"},
{"op" : "String"}], "return" : {"op" : "String"}, "purity" : "Effectful"}}, "args" : [{"op" : "Var", "id" : "tmp5225", "type" : {"op" : "String"}}, {"op" : "Literal", "type" : {"op" : "String"}, "value" : " in string: '"}]},
"export_as" : ["tmp"]}],
"body" : {"op" : "Let",
"definitions" : [{"name" : {"id" : "tmp5227", "type" : {"op" : "String"}},
"value" : {"op" : "App", "fn" : {"op" : "Var", "id" : "infixConcat35", "type" : {"op" : "Function", "params" : [{"op" : "String"},
{"op" : "String"}], "return" : {"op" : "String"}, "purity" : "Effectful"}}, "args" : [{"op" : "Var", "id" : "tmp5226", "type" : {"op" : "String"}}, {"op" : "Var", "id" : "str2473", "type" : {"op" : "String"}}]},
"export_as" : ["tmp"]}],
"body" : {"op" : "Let",
"definitions" : [{"name" : {"id" : "tmp5228", "type" : {"op" : "String"}},
"value" : {"op" : "App", "fn" : {"op" : "Var", "id" : "infixConcat35", "type" : {"op" : "Function", "params" : [{"op" : "String"},
{"op" : "String"}], "return" : {"op" : "String"}, "purity" : "Effectful"}}, "args" : [{"op" : "Var", "id" : "tmp5227", "type" : {"op" : "String"}}, {"op" : "Literal", "type" : {"op" : "String"}, "value" : "'"}]},
"export_as" : ["tmp"]}],
"body" : {"op" : "Invoke", "receiver" : {"op" : "Var", "id" : "Exception2728", "type" : {"op" : "Codata", "interface_tag" : "Exception532", "methods" : [{"tag" : "raise602", "params" : [{"op" : "Top"}, {"op" : "String"}], "return" : {"op" : "Bottom"}}]}}, "ifce_tag" : "Exception532", "tag" : "raise602", "args" : [{"op" : "Var", "id" : "tmp5223", "type" : {"op" : "Data", "type_tag" : "OutOfBounds541", "constructors" : [{"tag" : "OutOfBounds604", "fields" : []}]}}, {"op" : "Var", "id" : "tmp5228", "type" : {"op" : "String"}}]}}}}}}}}}}},
"export_as" : ["charAt"]},
{"name" : {"id" : "main2837", "type" : {"op" : "Function", "params" : [], "return" : {"op" : "Unit"}, "purity" : "Effectful"}},
"value" : {"op" : "Abs",
"params" : [],
"body" : {"op" : "Let",
"definitions" : [{"name" : {"id" : "n2850", "type" : {"op" : "Int"}},
"value" : {"op" : "Let",
"definitions" : [{"name" : {"id" : "p_8_94728", "type" : {"op" : "Label"}},
"value" : {"op" : "FreshLabel"},
"export_as" : ["p_8_9"]}],
"body" : {"op" : "Reset",
"label" : {"op" : "Var", "id" : "p_8_94728", "type" : {"op" : "Label"}},
"region" : {"id" : "v_tmp_52815310", "type" : {"op" : "Ptr"}},
"body" : {"op" : "LetRec",
"definitions" : [{"name" : {"id" : "toList_1_1_34776", "type" : {"op" : "Function", "params" : [{"op" : "Int"},
{"op" : "Data", "type_tag" : "List916", "constructors" : [{"tag" : "Nil1153", "fields" : []}, {"tag" : "Cons1154", "fields" : [{"op" : "Top"}, {"op" : "Data", "type_tag" : "List916", "constructors" : [{"tag" : "Nil1153", "fields" : []}, {"tag" : "Cons1154", "fields" : [{"op" : "Top"}, {"op" : "Ptr"}]}]}]}]}], "return" : {"op" : "Data", "type_tag" : "List916", "constructors" : [{"tag" : "Nil1153", "fields" : []}, {"tag" : "Cons1154", "fields" : [{"op" : "Top"}, {"op" : "Data", "type_tag" : "List916", "constructors" : [{"tag" : "Nil1153", "fields" : []}, {"tag" : "Cons1154", "fields" : [{"op" : "Top"}, {"op" : "Ptr"}]}]}]}]}, "purity" : "Effectful"}},
"value" : {"op" : "Abs",
"params" : [{"id" : "start_2_2_44755", "type" : {"op" : "Int"}}, {"id" : "acc_3_3_54812", "type" : {"op" : "Data", "type_tag" : "List916", "constructors" : [{"tag" : "Nil1153", "fields" : []}, {"tag" : "Cons1154", "fields" : [{"op" : "Top"}, {"op" : "Data", "type_tag" : "List916", "constructors" : [{"tag" : "Nil1153", "fields" : []}, {"tag" : "Cons1154", "fields" : [{"op" : "Top"}, {"op" : "Ptr"}]}]}]}]}}],
"body" : {"op" : "Let",
"definitions" : [{"name" : {"id" : "tmp5258", "type" : {"op" : "Bool"}},
"value" : {"op" : "App", "fn" : {"op" : "Var", "id" : "infixLt178", "type" : {"op" : "Function", "params" : [{"op" : "Int"},
{"op" : "Int"}], "return" : {"op" : "Bool"}, "purity" : "Effectful"}}, "args" : [{"op" : "Var", "id" : "start_2_2_44755", "type" : {"op" : "Int"}}, {"op" : "Literal", "type" : {"op" : "Int"}, "value" : 0}]},
"export_as" : ["tmp"]}],
"body" : {"op" : "IfZero",
"cond" : {"op" : "Var", "id" : "tmp5258", "type" : {"op" : "Bool"}},
"then" : {"op" : "Let",
"definitions" : [{"name" : {"id" : "tmp5230", "type" : {"op" : "String"}},
"value" : {"op" : "App", "fn" : {"op" : "Var", "id" : "argument2769", "type" : {"op" : "Function", "params" : [{"op" : "Int"}], "return" : {"op" : "String"}, "purity" : "Effectful"}}, "args" : [{"op" : "Var", "id" : "start_2_2_44755", "type" : {"op" : "Int"}}]},
"export_as" : ["tmp"]}],
"body" : {"op" : "Let",
"definitions" : [{"name" : {"id" : "tmp5231", "type" : {"op" : "Int"}},
"value" : {"op" : "App", "fn" : {"op" : "Var", "id" : "infixSub105", "type" : {"op" : "Function", "params" : [{"op" : "Int"},
{"op" : "Int"}], "return" : {"op" : "Int"}, "purity" : "Effectful"}}, "args" : [{"op" : "Var", "id" : "start_2_2_44755", "type" : {"op" : "Int"}}, {"op" : "Literal", "type" : {"op" : "Int"}, "value" : 1}]},
"export_as" : ["tmp"]}],
"body" : {"op" : "Let",
"definitions" : [{"name" : {"id" : "tmp5232", "type" : {"op" : "Data", "type_tag" : "List916", "constructors" : [{"tag" : "Nil1153", "fields" : []}, {"tag" : "Cons1154", "fields" : [{"op" : "Top"}, {"op" : "Data", "type_tag" : "List916", "constructors" : [{"tag" : "Nil1153", "fields" : []}, {"tag" : "Cons1154", "fields" : [{"op" : "Top"}, {"op" : "Ptr"}]}]}]}]}},
"value" : {"op" : "The",
"type" : {"op" : "Data", "type_tag" : "List916", "constructors" : [{"tag" : "Nil1153", "fields" : []}, {"tag" : "Cons1154", "fields" : [{"op" : "Top"}, {"op" : "Data", "type_tag" : "List916", "constructors" : [{"tag" : "Nil1153", "fields" : []}, {"tag" : "Cons1154", "fields" : [{"op" : "Top"}, {"op" : "Ptr"}]}]}]}]},
"term" : {"op" : "Construct", "type_tag" : "List916", "tag" : "Cons1154", "args" : [{"op" : "Var", "id" : "tmp5230", "type" : {"op" : "String"}}, {"op" : "Var", "id" : "acc_3_3_54812", "type" : {"op" : "Data", "type_tag" : "List916", "constructors" : [{"tag" : "Nil1153", "fields" : []}, {"tag" : "Cons1154", "fields" : [{"op" : "Top"}, {"op" : "Data", "type_tag" : "List916", "constructors" : [{"tag" : "Nil1153", "fields" : []}, {"tag" : "Cons1154", "fields" : [{"op" : "Top"}, {"op" : "Ptr"}]}]}]}]}}]}},
"export_as" : ["tmp"]}],
"body" : {"op" : "App", "fn" : {"op" : "Var", "id" : "toList_1_1_34776", "type" : {"op" : "Function", "params" : [{"op" : "Int"},
{"op" : "Data", "type_tag" : "List916", "constructors" : [{"tag" : "Nil1153", "fields" : []}, {"tag" : "Cons1154", "fields" : [{"op" : "Top"}, {"op" : "Data", "type_tag" : "List916", "constructors" : [{"tag" : "Nil1153", "fields" : []}, {"tag" : "Cons1154", "fields" : [{"op" : "Top"}, {"op" : "Ptr"}]}]}]}]}], "return" : {"op" : "Data", "type_tag" : "List916", "constructors" : [{"tag" : "Nil1153", "fields" : []}, {"tag" : "Cons1154", "fields" : [{"op" : "Top"}, {"op" : "Data", "type_tag" : "List916", "constructors" : [{"tag" : "Nil1153", "fields" : []}, {"tag" : "Cons1154", "fields" : [{"op" : "Top"}, {"op" : "Ptr"}]}]}]}]}, "purity" : "Effectful"}}, "args" : [{"op" : "Var", "id" : "tmp5231", "type" : {"op" : "Int"}}, {"op" : "Var", "id" : "tmp5232", "type" : {"op" : "Data", "type_tag" : "List916", "constructors" : [{"tag" : "Nil1153", "fields" : []}, {"tag" : "Cons1154", "fields" : [{"op" : "Top"}, {"op" : "Data", "type_tag" : "List916", "constructors" : [{"tag" : "Nil1153", "fields" : []}, {"tag" : "Cons1154", "fields" : [{"op" : "Top"}, {"op" : "Ptr"}]}]}]}]}}]}}}},
"else" : {"op" : "Var", "id" : "acc_3_3_54812", "type" : {"op" : "Data", "type_tag" : "List916", "constructors" : [{"tag" : "Nil1153", "fields" : []}, {"tag" : "Cons1154", "fields" : [{"op" : "Top"}, {"op" : "Data", "type_tag" : "List916", "constructors" : [{"tag" : "Nil1153", "fields" : []}, {"tag" : "Cons1154", "fields" : [{"op" : "Top"}, {"op" : "Ptr"}]}]}]}]}}}}},
"export_as" : ["toList_1_1_3"]}],
"body" : {"op" : "Let",
"definitions" : [{"name" : {"id" : "tmp5257", "type" : {"op" : "Int"}},
"value" : {"op" : "App", "fn" : {"op" : "Var", "id" : "argCount2767", "type" : {"op" : "Function", "params" : [], "return" : {"op" : "Int"}, "purity" : "Effectful"}}, "args" : []},
"export_as" : ["tmp"]}],
"body" : {"op" : "Let",
"definitions" : [{"name" : {"id" : "tmp5233", "type" : {"op" : "Int"}},
"value" : {"op" : "App", "fn" : {"op" : "Var", "id" : "infixSub105", "type" : {"op" : "Function", "params" : [{"op" : "Int"},
{"op" : "Int"}], "return" : {"op" : "Int"}, "purity" : "Effectful"}}, "args" : [{"op" : "Var", "id" : "tmp5257", "type" : {"op" : "Int"}}, {"op" : "Literal", "type" : {"op" : "Int"}, "value" : 1}]},
"export_as" : ["tmp"]}],
"body" : {"op" : "Let",
"definitions" : [{"name" : {"id" : "tmp5234", "type" : {"op" : "Data", "type_tag" : "List916", "constructors" : [{"tag" : "Nil1153", "fields" : []}, {"tag" : "Cons1154", "fields" : [{"op" : "Top"}, {"op" : "Data", "type_tag" : "List916", "constructors" : [{"tag" : "Nil1153", "fields" : []}, {"tag" : "Cons1154", "fields" : [{"op" : "Top"}, {"op" : "Ptr"}]}]}]}]}},
"value" : {"op" : "The",
"type" : {"op" : "Data", "type_tag" : "List916", "constructors" : [{"tag" : "Nil1153", "fields" : []}, {"tag" : "Cons1154", "fields" : [{"op" : "Top"}, {"op" : "Data", "type_tag" : "List916", "constructors" : [{"tag" : "Nil1153", "fields" : []}, {"tag" : "Cons1154", "fields" : [{"op" : "Top"}, {"op" : "Ptr"}]}]}]}]},
"term" : {"op" : "Construct", "type_tag" : "List916", "tag" : "Nil1153", "args" : []}},
"export_as" : ["tmp"]}],
"body" : {"op" : "Let",
"definitions" : [{"name" : {"id" : "v_r_3002_134766", "type" : {"op" : "Data", "type_tag" : "List916", "constructors" : [{"tag" : "Nil1153", "fields" : []}, {"tag" : "Cons1154", "fields" : [{"op" : "Top"}, {"op" : "Data", "type_tag" : "List916", "constructors" : [{"tag" : "Nil1153", "fields" : []}, {"tag" : "Cons1154", "fields" : [{"op" : "Top"}, {"op" : "Ptr"}]}]}]}]}},
"value" : {"op" : "App", "fn" : {"op" : "Var", "id" : "toList_1_1_34776", "type" : {"op" : "Function", "params" : [{"op" : "Int"},
{"op" : "Data", "type_tag" : "List916", "constructors" : [{"tag" : "Nil1153", "fields" : []}, {"tag" : "Cons1154", "fields" : [{"op" : "Top"}, {"op" : "Data", "type_tag" : "List916", "constructors" : [{"tag" : "Nil1153", "fields" : []}, {"tag" : "Cons1154", "fields" : [{"op" : "Top"}, {"op" : "Ptr"}]}]}]}]}], "return" : {"op" : "Data", "type_tag" : "List916", "constructors" : [{"tag" : "Nil1153", "fields" : []}, {"tag" : "Cons1154", "fields" : [{"op" : "Top"}, {"op" : "Data", "type_tag" : "List916", "constructors" : [{"tag" : "Nil1153", "fields" : []}, {"tag" : "Cons1154", "fields" : [{"op" : "Top"}, {"op" : "Ptr"}]}]}]}]}, "purity" : "Effectful"}}, "args" : [{"op" : "Var", "id" : "tmp5233", "type" : {"op" : "Int"}}, {"op" : "Var", "id" : "tmp5234", "type" : {"op" : "Data", "type_tag" : "List916", "constructors" : [{"tag" : "Nil1153", "fields" : []}, {"tag" : "Cons1154", "fields" : [{"op" : "Top"}, {"op" : "Data", "type_tag" : "List916", "constructors" : [{"tag" : "Nil1153", "fields" : []}, {"tag" : "Cons1154", "fields" : [{"op" : "Top"}, {"op" : "Ptr"}]}]}]}]}}]},
"export_as" : ["v_r_3002_13"]}],
"body" : {"op" : "Let",
"definitions" : [{"name" : {"id" : "v_r_3003_244822", "type" : {"op" : "Data", "type_tag" : "Option749", "constructors" : [{"tag" : "None803", "fields" : []}, {"tag" : "Some804", "fields" : [{"op" : "Top"}]}]}},
"value" : {"op" : "Match",
"scrutinee" : {"op" : "Var", "id" : "v_r_3002_134766", "type" : {"op" : "Data", "type_tag" : "List916", "constructors" : [{"tag" : "Nil1153", "fields" : []}, {"tag" : "Cons1154", "fields" : [{"op" : "Top"}, {"op" : "Data", "type_tag" : "List916", "constructors" : [{"tag" : "Nil1153", "fields" : []}, {"tag" : "Cons1154", "fields" : [{"op" : "Top"}, {"op" : "Ptr"}]}]}]}]}},
"type_tag" : "List916",
"clauses" : [{"tag" : "Nil1153",
"params" : [],
"body" : {"op" : "Let",
"definitions" : [{"name" : {"id" : "tmp5235", "type" : {"op" : "Data", "type_tag" : "Option749", "constructors" : [{"tag" : "None803", "fields" : []}, {"tag" : "Some804", "fields" : [{"op" : "Top"}]}]}},
"value" : {"op" : "The",
"type" : {"op" : "Data", "type_tag" : "Option749", "constructors" : [{"tag" : "None803", "fields" : []}, {"tag" : "Some804", "fields" : [{"op" : "Top"}]}]},
"term" : {"op" : "Construct", "type_tag" : "Option749", "tag" : "None803", "args" : []}},
"export_as" : ["tmp"]}],
"body" : {"op" : "Var", "id" : "tmp5235", "type" : {"op" : "Data", "type_tag" : "Option749", "constructors" : [{"tag" : "None803", "fields" : []}, {"tag" : "Some804", "fields" : [{"op" : "Top"}]}]}}}},
{"tag" : "Cons1154",
"params" : [{"id" : "v_y_3328_10_214793", "type" : {"op" : "String"}}, {"id" : "v_y_3329_11_224753", "type" : {"op" : "Data", "type_tag" : "List916", "constructors" : [{"tag" : "Nil1153", "fields" : []}, {"tag" : "Cons1154", "fields" : [{"op" : "Top"}, {"op" : "Data", "type_tag" : "List916", "constructors" : [{"tag" : "Nil1153", "fields" : []}, {"tag" : "Cons1154", "fields" : [{"op" : "Top"}, {"op" : "Ptr"}]}]}]}]}}],
"body" : {"op" : "Let",
"definitions" : [{"name" : {"id" : "tmp5236", "type" : {"op" : "Data", "type_tag" : "Option749", "constructors" : [{"tag" : "None803", "fields" : []}, {"tag" : "Some804", "fields" : [{"op" : "Top"}]}]}},
"value" : {"op" : "The",
"type" : {"op" : "Data", "type_tag" : "Option749", "constructors" : [{"tag" : "None803", "fields" : []}, {"tag" : "Some804", "fields" : [{"op" : "Top"}]}]},
"term" : {"op" : "Construct", "type_tag" : "Option749", "tag" : "Some804", "args" : [{"op" : "Var", "id" : "v_y_3328_10_214793", "type" : {"op" : "String"}}]}},
"export_as" : ["tmp"]}],
"body" : {"op" : "Var", "id" : "tmp5236", "type" : {"op" : "Data", "type_tag" : "Option749", "constructors" : [{"tag" : "None803", "fields" : []}, {"tag" : "Some804", "fields" : [{"op" : "Top"}]}]}}}}],
"default_clause" : {"params" : [],
"body" : {"op" : "Primitive",
"name" : "non-exhaustive match",
"args" : [],
"returns" : [{"id" : "%bottom", "type" : {"op" : "Bottom"}}],
"rest" : {"op" : "Var", "id" : "%bottom", "type" : {"op" : "Bottom"}}}}},
"export_as" : ["v_r_3003_24"]}],
"body" : {"op" : "Let",
"definitions" : [{"name" : {"id" : "v_r_3004_304744", "type" : {"op" : "String"}},
"value" : {"op" : "Match",
"scrutinee" : {"op" : "Var", "id" : "v_r_3003_244822", "type" : {"op" : "Data", "type_tag" : "Option749", "constructors" : [{"tag" : "None803", "fields" : []}, {"tag" : "Some804", "fields" : [{"op" : "Top"}]}]}},
"type_tag" : "Option749",
"clauses" : [{"tag" : "None803",
"params" : [],
"body" : {"op" : "Literal", "type" : {"op" : "String"}, "value" : ""}},
{"tag" : "Some804",
"params" : [{"id" : "v_y_3819_8_294762", "type" : {"op" : "String"}}],
"body" : {"op" : "Var", "id" : "v_y_3819_8_294762", "type" : {"op" : "String"}}}],
"default_clause" : {"params" : [],
"body" : {"op" : "Primitive",
"name" : "non-exhaustive match",
"args" : [],
"returns" : [{"id" : "%bottom", "type" : {"op" : "Bottom"}}],
"rest" : {"op" : "Var", "id" : "%bottom", "type" : {"op" : "Bottom"}}}}},
"export_as" : ["v_r_3004_30"]}],
"body" : {"op" : "Let",
"definitions" : [{"name" : {"id" : "tmp5237", "type" : {"op" : "Int"}},
"value" : {"op" : "App", "fn" : {"op" : "Var", "id" : "toInt2452", "type" : {"op" : "Function", "params" : [{"op" : "String"}], "return" : {"op" : "Int"}, "purity" : "Effectful"}}, "args" : [{"op" : "Literal", "type" : {"op" : "String"}, "value" : "0"}]},
"export_as" : ["tmp"]}],
"body" : {"op" : "LetRec",
"definitions" : [{"name" : {"id" : "go_6_334778", "type" : {"op" : "Function", "params" : [{"op" : "Int"},
{"op" : "Int"}], "return" : {"op" : "Int"}, "purity" : "Effectful"}},
"value" : {"op" : "Abs",
"params" : [{"id" : "index_7_344769", "type" : {"op" : "Int"}}, {"id" : "acc_8_354752", "type" : {"op" : "Int"}}],
"body" : {"op" : "Let",
"definitions" : [{"name" : {"id" : "v_r_3087_22_494810", "type" : {"op" : "Data", "type_tag" : "Result1949", "constructors" : [{"tag" : "Error1967", "fields" : [{"op" : "Top"}, {"op" : "String"}]}, {"tag" : "Success1972", "fields" : [{"op" : "Top"}]}]}},
"value" : {"op" : "Let",
"definitions" : [{"name" : {"id" : "p_6_13_404815", "type" : {"op" : "Label"}},
"value" : {"op" : "FreshLabel"},
"export_as" : ["p_6_13_40"]}],
"body" : {"op" : "Reset",
"label" : {"op" : "Var", "id" : "p_6_13_404815", "type" : {"op" : "Label"}},
"region" : {"id" : "v_tmp_52835311", "type" : {"op" : "Ptr"}},
"body" : {"op" : "LetRec",
"definitions" : [{"name" : {"id" : "Exception_7_14_414796", "type" : {"op" : "Codata", "interface_tag" : "Exception532", "methods" : [{"tag" : "raise602", "params" : [{"op" : "Top"}, {"op" : "String"}], "return" : {"op" : "Bottom"}}]}},
"value" : {"op" : "New",
"ifce_tag" : "Exception532_Data(OutOfBounds,List())",
"methods" : [{"tag" : "raise602",
"params" : [{"id" : "exc_8_15_424768", "type" : {"op" : "Data", "type_tag" : "OutOfBounds541", "constructors" : [{"tag" : "OutOfBounds604", "fields" : []}]}}, {"id" : "msg_9_16_434774", "type" : {"op" : "String"}}],
"body" : {"op" : "Shift",
"label" : {"op" : "Var", "id" : "p_6_13_404815", "type" : {"op" : "Label"}},
"n" : {"op" : "Literal", "type" : {"op" : "Int"}, "value" : 0},
"k" : {"id" : "k_11_18_454835", "type" : {"op" : "Stack", "resume_return" : {"op" : "Data", "type_tag" : "Result1949", "constructors" : [{"tag" : "Error1967", "fields" : [{"op" : "Top"}, {"op" : "String"}]}, {"tag" : "Success1972", "fields" : [{"op" : "Top"}]}]}, "resume_args" : [{"op" : "Bottom"}]}},
"returnType" : {"op" : "Data", "type_tag" : "Result1949", "constructors" : [{"tag" : "Error1967", "fields" : [{"op" : "Top"}, {"op" : "String"}]}, {"tag" : "Success1972", "fields" : [{"op" : "Top"}]}]},
"body" : {"op" : "Let",
"definitions" : [{"name" : {"id" : "tmp5238", "type" : {"op" : "Data", "type_tag" : "Result1949", "constructors" : [{"tag" : "Error1967", "fields" : [{"op" : "Top"}, {"op" : "String"}]}, {"tag" : "Success1972", "fields" : [{"op" : "Top"}]}]}},
"value" : {"op" : "The",
"type" : {"op" : "Data", "type_tag" : "Result1949", "constructors" : [{"tag" : "Error1967", "fields" : [{"op" : "Top"}, {"op" : "String"}]}, {"tag" : "Success1972", "fields" : [{"op" : "Top"}]}]},
"term" : {"op" : "Construct", "type_tag" : "Result1949", "tag" : "Error1967", "args" : [{"op" : "Var", "id" : "exc_8_15_424768", "type" : {"op" : "Data", "type_tag" : "OutOfBounds541", "constructors" : [{"tag" : "OutOfBounds604", "fields" : []}]}}, {"op" : "Var", "id" : "msg_9_16_434774", "type" : {"op" : "String"}}]}},
"export_as" : ["tmp"]}],
"body" : {"op" : "Var", "id" : "tmp5238", "type" : {"op" : "Data", "type_tag" : "Result1949", "constructors" : [{"tag" : "Error1967", "fields" : [{"op" : "Top"}, {"op" : "String"}]}, {"tag" : "Success1972", "fields" : [{"op" : "Top"}]}]}}}}}]},
"export_as" : ["Exception_7_14_41"]}],
"body" : {"op" : "Let",
"definitions" : [{"name" : {"id" : "v_r_3263_13_20_474828", "type" : {"op" : "String"}},
"value" : {"op" : "App", "fn" : {"op" : "Var", "id" : "charAt2475", "type" : {"op" : "Function", "params" : [{"op" : "String"},
{"op" : "Int"},
{"op" : "Codata", "interface_tag" : "Exception532", "methods" : [{"tag" : "raise602", "params" : [{"op" : "Top"}, {"op" : "String"}], "return" : {"op" : "Bottom"}}]}], "return" : {"op" : "String"}, "purity" : "Effectful"}}, "args" : [{"op" : "Var", "id" : "v_r_3004_304744", "type" : {"op" : "String"}}, {"op" : "Var", "id" : "index_7_344769", "type" : {"op" : "Int"}}, {"op" : "Var", "id" : "Exception_7_14_414796", "type" : {"op" : "Codata", "interface_tag" : "Exception532", "methods" : [{"tag" : "raise602", "params" : [{"op" : "Top"}, {"op" : "String"}], "return" : {"op" : "Bottom"}}]}}]},
"export_as" : ["v_r_3263_13_20_47"]}],
"body" : {"op" : "Let",
"definitions" : [{"name" : {"id" : "tmp5239", "type" : {"op" : "Data", "type_tag" : "Result1949", "constructors" : [{"tag" : "Error1967", "fields" : [{"op" : "Top"}, {"op" : "String"}]}, {"tag" : "Success1972", "fields" : [{"op" : "Top"}]}]}},
"value" : {"op" : "The",
"type" : {"op" : "Data", "type_tag" : "Result1949", "constructors" : [{"tag" : "Error1967", "fields" : [{"op" : "Top"}, {"op" : "String"}]}, {"tag" : "Success1972", "fields" : [{"op" : "Top"}]}]},
"term" : {"op" : "Construct", "type_tag" : "Result1949", "tag" : "Success1972", "args" : [{"op" : "Var", "id" : "v_r_3263_13_20_474828", "type" : {"op" : "String"}}]}},
"export_as" : ["tmp"]}],
"body" : {"op" : "Var", "id" : "tmp5239", "type" : {"op" : "Data", "type_tag" : "Result1949", "constructors" : [{"tag" : "Error1967", "fields" : [{"op" : "Top"}, {"op" : "String"}]}, {"tag" : "Success1972", "fields" : [{"op" : "Top"}]}]}}}}},
"return" : {"params" : [{"id" : "v_tmp_52825312", "type" : {"op" : "Data", "type_tag" : "Result1949", "constructors" : [{"tag" : "Error1967", "fields" : [{"op" : "Top"}, {"op" : "String"}]}, {"tag" : "Success1972", "fields" : [{"op" : "Top"}]}]}}],
"body" : {"op" : "Var", "id" : "v_tmp_52825312", "type" : {"op" : "Data", "type_tag" : "Result1949", "constructors" : [{"tag" : "Error1967", "fields" : [{"op" : "Top"}, {"op" : "String"}]}, {"tag" : "Success1972", "fields" : [{"op" : "Top"}]}]}}}}},
"export_as" : ["v_r_3087_22_49"]}],
"body" : {"op" : "Match",
"scrutinee" : {"op" : "Var", "id" : "v_r_3087_22_494810", "type" : {"op" : "Data", "type_tag" : "Result1949", "constructors" : [{"tag" : "Error1967", "fields" : [{"op" : "Top"}, {"op" : "String"}]}, {"tag" : "Success1972", "fields" : [{"op" : "Top"}]}]}},
"type_tag" : "Result1949",
"clauses" : [{"tag" : "Success1972",
"params" : [{"id" : "v_y_3093_36_634808", "type" : {"op" : "String"}}],
"body" : {"op" : "Let",
"definitions" : [{"name" : {"id" : "tmp5240", "type" : {"op" : "Bool"}},
"value" : {"op" : "App", "fn" : {"op" : "Var", "id" : "infixGte2466", "type" : {"op" : "Function", "params" : [{"op" : "String"},
{"op" : "String"}], "return" : {"op" : "Bool"}, "purity" : "Effectful"}}, "args" : [{"op" : "Var", "id" : "v_y_3093_36_634808", "type" : {"op" : "String"}}, {"op" : "Literal", "type" : {"op" : "String"}, "value" : "0"}]},
"export_as" : ["tmp"]}],
"body" : {"op" : "IfZero",
"cond" : {"op" : "Var", "id" : "tmp5240", "type" : {"op" : "Bool"}},
"then" : {"op" : "Shift",
"label" : {"op" : "Var", "id" : "p_8_94728", "type" : {"op" : "Label"}},
"n" : {"op" : "Literal", "type" : {"op" : "Int"}, "value" : 0},
"k" : {"id" : "k_13_14_45313", "type" : {"op" : "Stack", "resume_return" : {"op" : "Int"}, "resume_args" : [{"op" : "Bottom"}]}},
"returnType" : {"op" : "Int"},
"body" : {"op" : "Literal", "type" : {"op" : "Int"}, "value" : 5}},
"else" : {"op" : "Let",
"definitions" : [{"name" : {"id" : "tmp5241", "type" : {"op" : "Bool"}},
"value" : {"op" : "App", "fn" : {"op" : "Var", "id" : "infixLte2460", "type" : {"op" : "Function", "params" : [{"op" : "String"},
{"op" : "String"}], "return" : {"op" : "Bool"}, "purity" : "Effectful"}}, "args" : [{"op" : "Var", "id" : "v_y_3093_36_634808", "type" : {"op" : "String"}}, {"op" : "Literal", "type" : {"op" : "String"}, "value" : "9"}]},
"export_as" : ["tmp"]}],
"body" : {"op" : "IfZero",
"cond" : {"op" : "Var", "id" : "tmp5241", "type" : {"op" : "Bool"}},
"then" : {"op" : "Shift",
"label" : {"op" : "Var", "id" : "p_8_94728", "type" : {"op" : "Label"}},
"n" : {"op" : "Literal", "type" : {"op" : "Int"}, "value" : 0},
"k" : {"id" : "k_13_14_45314", "type" : {"op" : "Stack", "resume_return" : {"op" : "Int"}, "resume_args" : [{"op" : "Bottom"}]}},
"returnType" : {"op" : "Int"},
"body" : {"op" : "Literal", "type" : {"op" : "Int"}, "value" : 5}},
"else" : {"op" : "Let",
"definitions" : [{"name" : {"id" : "tmp5242", "type" : {"op" : "Int"}},
"value" : {"op" : "App", "fn" : {"op" : "Var", "id" : "infixAdd96", "type" : {"op" : "Function", "params" : [{"op" : "Int"},
{"op" : "Int"}], "return" : {"op" : "Int"}, "purity" : "Effectful"}}, "args" : [{"op" : "Var", "id" : "index_7_344769", "type" : {"op" : "Int"}}, {"op" : "Literal", "type" : {"op" : "Int"}, "value" : 1}]},
"export_as" : ["tmp"]}],
"body" : {"op" : "Let",
"definitions" : [{"name" : {"id" : "tmp5243", "type" : {"op" : "Int"}},
"value" : {"op" : "App", "fn" : {"op" : "Var", "id" : "infixMul99", "type" : {"op" : "Function", "params" : [{"op" : "Int"},
{"op" : "Int"}], "return" : {"op" : "Int"}, "purity" : "Effectful"}}, "args" : [{"op" : "Literal", "type" : {"op" : "Int"}, "value" : 10}, {"op" : "Var", "id" : "acc_8_354752", "type" : {"op" : "Int"}}]},
"export_as" : ["tmp"]}],
"body" : {"op" : "Let",
"definitions" : [{"name" : {"id" : "tmp5244", "type" : {"op" : "Int"}},
"value" : {"op" : "App", "fn" : {"op" : "Var", "id" : "toInt2452", "type" : {"op" : "Function", "params" : [{"op" : "String"}], "return" : {"op" : "Int"}, "purity" : "Effectful"}}, "args" : [{"op" : "Var", "id" : "v_y_3093_36_634808", "type" : {"op" : "String"}}]},
"export_as" : ["tmp"]}],
"body" : {"op" : "Let",
"definitions" : [{"name" : {"id" : "tmp5245", "type" : {"op" : "Int"}},
"value" : {"op" : "App", "fn" : {"op" : "Var", "id" : "infixSub105", "type" : {"op" : "Function", "params" : [{"op" : "Int"},
{"op" : "Int"}], "return" : {"op" : "Int"}, "purity" : "Effectful"}}, "args" : [{"op" : "Var", "id" : "tmp5244", "type" : {"op" : "Int"}}, {"op" : "Var", "id" : "tmp5237", "type" : {"op" : "Int"}}]},
"export_as" : ["tmp"]}],
"body" : {"op" : "Let",
"definitions" : [{"name" : {"id" : "tmp5246", "type" : {"op" : "Int"}},
"value" : {"op" : "App", "fn" : {"op" : "Var", "id" : "infixAdd96", "type" : {"op" : "Function", "params" : [{"op" : "Int"},
{"op" : "Int"}], "return" : {"op" : "Int"}, "purity" : "Effectful"}}, "args" : [{"op" : "Var", "id" : "tmp5243", "type" : {"op" : "Int"}}, {"op" : "Var", "id" : "tmp5245", "type" : {"op" : "Int"}}]},
"export_as" : ["tmp"]}],
"body" : {"op" : "App", "fn" : {"op" : "Var", "id" : "go_6_334778", "type" : {"op" : "Function", "params" : [{"op" : "Int"},
{"op" : "Int"}], "return" : {"op" : "Int"}, "purity" : "Effectful"}}, "args" : [{"op" : "Var", "id" : "tmp5242", "type" : {"op" : "Int"}}, {"op" : "Var", "id" : "tmp5246", "type" : {"op" : "Int"}}]}}}}}}}}}}},
{"tag" : "Error1967",
"params" : [{"id" : "v_y_3094_50_775315", "type" : {"op" : "Data", "type_tag" : "OutOfBounds541", "constructors" : [{"tag" : "OutOfBounds604", "fields" : []}]}}, {"id" : "v_y_3095_51_785316", "type" : {"op" : "String"}}],
"body" : {"op" : "Var", "id" : "acc_8_354752", "type" : {"op" : "Int"}}}],
"default_clause" : {"params" : [],
"body" : {"op" : "Primitive",
"name" : "non-exhaustive match",
"args" : [],
"returns" : [{"id" : "%bottom", "type" : {"op" : "Bottom"}}],
"rest" : {"op" : "Var", "id" : "%bottom", "type" : {"op" : "Bottom"}}}}}}},
"export_as" : ["go_6_33"]}],
"body" : {"op" : "LetRec",
"definitions" : [{"name" : {"id" : "Exception_9_67_944799", "type" : {"op" : "Codata", "interface_tag" : "Exception532", "methods" : [{"tag" : "raise602", "params" : [{"op" : "Top"}, {"op" : "String"}], "return" : {"op" : "Bottom"}}]}},
"value" : {"op" : "New",
"ifce_tag" : "Exception532_Data(OutOfBounds,List())",
"methods" : [{"tag" : "raise602",
"params" : [{"id" : "exception_10_68_955317", "type" : {"op" : "Data", "type_tag" : "OutOfBounds541", "constructors" : [{"tag" : "OutOfBounds604", "fields" : []}]}}, {"id" : "msg_11_69_965318", "type" : {"op" : "String"}}],
"body" : {"op" : "Shift",
"label" : {"op" : "Var", "id" : "p_8_94728", "type" : {"op" : "Label"}},
"n" : {"op" : "Literal", "type" : {"op" : "Int"}, "value" : 0},
"k" : {"id" : "k_13_14_45319", "type" : {"op" : "Stack", "resume_return" : {"op" : "Int"}, "resume_args" : [{"op" : "Bottom"}]}},
"returnType" : {"op" : "Int"},
"body" : {"op" : "Literal", "type" : {"op" : "Int"}, "value" : 5}}}]},
"export_as" : ["Exception_9_67_94"]}],
"body" : {"op" : "Let",
"definitions" : [{"name" : {"id" : "v_r_3100_3_73_1004824", "type" : {"op" : "String"}},
"value" : {"op" : "App", "fn" : {"op" : "Var", "id" : "charAt2475", "type" : {"op" : "Function", "params" : [{"op" : "String"},
{"op" : "Int"},
{"op" : "Codata", "interface_tag" : "Exception532", "methods" : [{"tag" : "raise602", "params" : [{"op" : "Top"}, {"op" : "String"}], "return" : {"op" : "Bottom"}}]}], "return" : {"op" : "String"}, "purity" : "Effectful"}}, "args" : [{"op" : "Var", "id" : "v_r_3004_304744", "type" : {"op" : "String"}}, {"op" : "Literal", "type" : {"op" : "Int"}, "value" : 0}, {"op" : "Var", "id" : "Exception_9_67_944799", "type" : {"op" : "Codata", "interface_tag" : "Exception532", "methods" : [{"tag" : "raise602", "params" : [{"op" : "Top"}, {"op" : "String"}], "return" : {"op" : "Bottom"}}]}}]},
"export_as" : ["v_r_3100_3_73_100"]}],
"body" : {"op" : "Let",
"definitions" : [{"name" : {"id" : "tmp5247", "type" : {"op" : "Bool"}},
"value" : {"op" : "App", "fn" : {"op" : "Var", "id" : "infixEq78", "type" : {"op" : "Function", "params" : [{"op" : "String"},
{"op" : "String"}], "return" : {"op" : "Bool"}, "purity" : "Effectful"}}, "args" : [{"op" : "Var", "id" : "v_r_3100_3_73_1004824", "type" : {"op" : "String"}}, {"op" : "Literal", "type" : {"op" : "String"}, "value" : "-"}]},
"export_as" : ["tmp"]}],
"body" : {"op" : "IfZero",
"cond" : {"op" : "Var", "id" : "tmp5247", "type" : {"op" : "Bool"}},
"then" : {"op" : "App", "fn" : {"op" : "Var", "id" : "go_6_334778", "type" : {"op" : "Function", "params" : [{"op" : "Int"},
{"op" : "Int"}], "return" : {"op" : "Int"}, "purity" : "Effectful"}}, "args" : [{"op" : "Literal", "type" : {"op" : "Int"}, "value" : 0}, {"op" : "Literal", "type" : {"op" : "Int"}, "value" : 0}]},
"else" : {"op" : "Let",
"definitions" : [{"name" : {"id" : "v_r_3101_1_9_79_1064751", "type" : {"op" : "Int"}},
"value" : {"op" : "App", "fn" : {"op" : "Var", "id" : "go_6_334778", "type" : {"op" : "Function", "params" : [{"op" : "Int"},
{"op" : "Int"}], "return" : {"op" : "Int"}, "purity" : "Effectful"}}, "args" : [{"op" : "Literal", "type" : {"op" : "Int"}, "value" : 1}, {"op" : "Literal", "type" : {"op" : "Int"}, "value" : 0}]},
"export_as" : ["v_r_3101_1_9_79_106"]}],
"body" : {"op" : "Let",
"definitions" : [{"name" : {"id" : "tmp5248", "type" : {"op" : "Int"}},
"value" : {"op" : "App", "fn" : {"op" : "Var", "id" : "infixSub105", "type" : {"op" : "Function", "params" : [{"op" : "Int"},
{"op" : "Int"}], "return" : {"op" : "Int"}, "purity" : "Effectful"}}, "args" : [{"op" : "Literal", "type" : {"op" : "Int"}, "value" : 0}, {"op" : "Var", "id" : "v_r_3101_1_9_79_1064751", "type" : {"op" : "Int"}}]},
"export_as" : ["tmp"]}],
"body" : {"op" : "Var", "id" : "tmp5248", "type" : {"op" : "Int"}}}}}}}}}}}}}}}}},
"return" : {"params" : [{"id" : "v_tmp_52805320", "type" : {"op" : "Int"}}],
"body" : {"op" : "Var", "id" : "v_tmp_52805320", "type" : {"op" : "Int"}}}}},
"export_as" : ["n"]}],
"body" : {"op" : "Let",
"definitions" : [{"name" : {"id" : "v_r_2959_3_1495034", "type" : {"op" : "Int"}},
"value" : {"op" : "Literal", "type" : {"op" : "Int"}, "value" : 0},
"export_as" : ["v_r_2959_3_149"]}],
"body" : {"op" : "Let",
"definitions" : [{"name" : {"id" : "r2851", "type" : {"op" : "Int"}},
"value" : {"op" : "Reset",
"label" : {"op" : "FreshLabel"},
"region" : {"id" : "b_tmp_52845321", "type" : {"op" : "Ptr"}},
"body" : {"op" : "LetRef",
"ref" : {"id" : "s_4_1505016", "type" : {"op" : "Ref", "to" : {"op" : "Int"}}},
"region" : {"op" : "Var", "id" : "b_tmp_52845321", "type" : {"op" : "Ptr"}},
"binding" : {"op" : "Var", "id" : "v_r_2959_3_1495034", "type" : {"op" : "Int"}},
"body" : {"op" : "Let",
"definitions" : [{"name" : {"id" : "__16_3345171", "type" : {"op" : "Unit"}},
"value" : {"op" : "Let",
"definitions" : [{"name" : {"id" : "p_4_71_2444977", "type" : {"op" : "Label"}},
"value" : {"op" : "FreshLabel"},
"export_as" : ["p_4_71_244"]}],
"body" : {"op" : "Reset",
"label" : {"op" : "Var", "id" : "p_4_71_2444977", "type" : {"op" : "Label"}},
"region" : {"id" : "v_tmp_52875322", "type" : {"op" : "Ptr"}},
"body" : {"op" : "Let",
"definitions" : [{"name" : {"id" : "v_r_2975_6_15_89_2695071", "type" : {"op" : "Int"}},
"value" : {"op" : "Literal", "type" : {"op" : "Int"}, "value" : 0},
"export_as" : ["v_r_2975_6_15_89_269"]}],
"body" : {"op" : "Reset",
"label" : {"op" : "FreshLabel"},
"region" : {"id" : "b_tmp_52885323", "type" : {"op" : "Ptr"}},
"body" : {"op" : "LetRef",
"ref" : {"id" : "i_7_16_90_2704974", "type" : {"op" : "Ref", "to" : {"op" : "Int"}}},
"region" : {"op" : "Var", "id" : "b_tmp_52885323", "type" : {"op" : "Ptr"}},
"binding" : {"op" : "Var", "id" : "v_r_2975_6_15_89_2695071", "type" : {"op" : "Int"}},
"body" : {"op" : "Let",
"definitions" : [{"name" : {"id" : "v_r_2976_8_17_91_2714999", "type" : {"op" : "Int"}},
"value" : {"op" : "Literal", "type" : {"op" : "Int"}, "value" : 0},
"export_as" : ["v_r_2976_8_17_91_271"]}],
"body" : {"op" : "Reset",
"label" : {"op" : "FreshLabel"},
"region" : {"id" : "b_tmp_52905324", "type" : {"op" : "Ptr"}},
"body" : {"op" : "LetRef",
"ref" : {"id" : "j_9_18_92_2724947", "type" : {"op" : "Ref", "to" : {"op" : "Int"}}},
"region" : {"op" : "Var", "id" : "b_tmp_52905324", "type" : {"op" : "Ptr"}},
"binding" : {"op" : "Var", "id" : "v_r_2976_8_17_91_2714999", "type" : {"op" : "Int"}},
"body" : {"op" : "LetRec",
"definitions" : [{"name" : {"id" : "parse_worker_8_3_40_116_2964906", "type" : {"op" : "Function", "params" : [{"op" : "Int"}], "return" : {"op" : "Unit"}, "purity" : "Effectful"}},
"value" : {"op" : "Abs",
"params" : [{"id" : "a_9_4_41_117_2975031", "type" : {"op" : "Int"}}],
"body" : {"op" : "Let",
"definitions" : [{"name" : {"id" : "v_r_2978_17_5_46_122_3024898", "type" : {"op" : "Int"}},
"value" : {"op" : "Load", "ref" : {"op" : "Var", "id" : "i_7_16_90_2704974", "type" : {"op" : "Ref", "to" : {"op" : "Int"}}}},
"export_as" : ["v_r_2978_17_5_46_122_302"]}],
"body" : {"op" : "Let",
"definitions" : [{"name" : {"id" : "tmp5260", "type" : {"op" : "Bool"}},
"value" : {"op" : "App", "fn" : {"op" : "Var", "id" : "infixGt184", "type" : {"op" : "Function", "params" : [{"op" : "Int"},
{"op" : "Int"}], "return" : {"op" : "Bool"}, "purity" : "Effectful"}}, "args" : [{"op" : "Var", "id" : "v_r_2978_17_5_46_122_3024898", "type" : {"op" : "Int"}}, {"op" : "Var", "id" : "n2850", "type" : {"op" : "Int"}}]},
"export_as" : ["tmp"]}],
"body" : {"op" : "Let",
"definitions" : [{"name" : {"id" : "c_10_5_60_138_3184978", "type" : {"op" : "Int"}},
"value" : {"op" : "IfZero",
"cond" : {"op" : "Var", "id" : "tmp5260", "type" : {"op" : "Bool"}},
"then" : {"op" : "Let",
"definitions" : [{"name" : {"id" : "v_r_2981_19_7_48_126_3065041", "type" : {"op" : "Int"}},
"value" : {"op" : "Load", "ref" : {"op" : "Var", "id" : "j_9_18_92_2724947", "type" : {"op" : "Ref", "to" : {"op" : "Int"}}}},
"export_as" : ["v_r_2981_19_7_48_126_306"]}],
"body" : {"op" : "Let",
"definitions" : [{"name" : {"id" : "tmp5249", "type" : {"op" : "Bool"}},
"value" : {"op" : "App", "fn" : {"op" : "Var", "id" : "infixEq72", "type" : {"op" : "Function", "params" : [{"op" : "Int"},
{"op" : "Int"}], "return" : {"op" : "Bool"}, "purity" : "Effectful"}}, "args" : [{"op" : "Var", "id" : "v_r_2981_19_7_48_126_3065041", "type" : {"op" : "Int"}}, {"op" : "Literal", "type" : {"op" : "Int"}, "value" : 0}]},
"export_as" : ["tmp"]}],
"body" : {"op" : "IfZero",
"cond" : {"op" : "Var", "id" : "tmp5249", "type" : {"op" : "Bool"}},
"then" : {"op" : "Let",
"definitions" : [{"name" : {"id" : "v_r_2988_27_15_56_134_3144993", "type" : {"op" : "Int"}},
"value" : {"op" : "Load", "ref" : {"op" : "Var", "id" : "j_9_18_92_2724947", "type" : {"op" : "Ref", "to" : {"op" : "Int"}}}},
"export_as" : ["v_r_2988_27_15_56_134_314"]}],
"body" : {"op" : "Let",
"definitions" : [{"name" : {"id" : "tmp5251", "type" : {"op" : "Int"}},
"value" : {"op" : "App", "fn" : {"op" : "Var", "id" : "infixSub105", "type" : {"op" : "Function", "params" : [{"op" : "Int"},
{"op" : "Int"}], "return" : {"op" : "Int"}, "purity" : "Effectful"}}, "args" : [{"op" : "Var", "id" : "v_r_2988_27_15_56_134_3144993", "type" : {"op" : "Int"}}, {"op" : "Literal", "type" : {"op" : "Int"}, "value" : 1}]},
"export_as" : ["tmp"]}],
"body" : {"op" : "Let",
"definitions" : [{"name" : {"id" : "__29_17_58_136_3165168", "type" : {"op" : "Unit"}},
"value" : {"op" : "Store", "ref" : {"op" : "Var", "id" : "j_9_18_92_2724947", "type" : {"op" : "Ref", "to" : {"op" : "Int"}}}, "value" : {"op" : "Var", "id" : "tmp5251", "type" : {"op" : "Int"}}},
"export_as" : ["__29_17_58_136_316"]}],
"body" : {"op" : "Let",
"definitions" : [{"name" : {"id" : "v_r_2990_30_18_59_137_3175091", "type" : {"op" : "Int"}},
"value" : {"op" : "Literal", "type" : {"op" : "Int"}, "value" : 36},
"export_as" : ["v_r_2990_30_18_59_137_317"]}],
"body" : {"op" : "Var", "id" : "v_r_2990_30_18_59_137_3175091", "type" : {"op" : "Int"}}}}}},
"else" : {"op" : "Let",
"definitions" : [{"name" : {"id" : "v_r_2982_21_9_50_128_3084965", "type" : {"op" : "Int"}},
"value" : {"op" : "Load", "ref" : {"op" : "Var", "id" : "i_7_16_90_2704974", "type" : {"op" : "Ref", "to" : {"op" : "Int"}}}},
"export_as" : ["v_r_2982_21_9_50_128_308"]}],
"body" : {"op" : "Let",
"definitions" : [{"name" : {"id" : "tmp5250", "type" : {"op" : "Int"}},
"value" : {"op" : "App", "fn" : {"op" : "Var", "id" : "infixAdd96", "type" : {"op" : "Function", "params" : [{"op" : "Int"},
{"op" : "Int"}], "return" : {"op" : "Int"}, "purity" : "Effectful"}}, "args" : [{"op" : "Var", "id" : "v_r_2982_21_9_50_128_3084965", "type" : {"op" : "Int"}}, {"op" : "Literal", "type" : {"op" : "Int"}, "value" : 1}]},
"export_as" : ["tmp"]}],
"body" : {"op" : "Let",
"definitions" : [{"name" : {"id" : "__23_11_52_130_3105166", "type" : {"op" : "Unit"}},
"value" : {"op" : "Store", "ref" : {"op" : "Var", "id" : "i_7_16_90_2704974", "type" : {"op" : "Ref", "to" : {"op" : "Int"}}}, "value" : {"op" : "Var", "id" : "tmp5250", "type" : {"op" : "Int"}}},
"export_as" : ["__23_11_52_130_310"]}],
"body" : {"op" : "Let",
"definitions" : [{"name" : {"id" : "v_r_2984_24_12_53_131_3114896", "type" : {"op" : "Int"}},
"value" : {"op" : "Load", "ref" : {"op" : "Var", "id" : "i_7_16_90_2704974", "type" : {"op" : "Ref", "to" : {"op" : "Int"}}}},
"export_as" : ["v_r_2984_24_12_53_131_311"]}],
"body" : {"op" : "Let",
"definitions" : [{"name" : {"id" : "__25_13_54_132_3125167", "type" : {"op" : "Unit"}},
"value" : {"op" : "Store", "ref" : {"op" : "Var", "id" : "j_9_18_92_2724947", "type" : {"op" : "Ref", "to" : {"op" : "Int"}}}, "value" : {"op" : "Var", "id" : "v_r_2984_24_12_53_131_3114896", "type" : {"op" : "Int"}}},
"export_as" : ["__25_13_54_132_312"]}],
"body" : {"op" : "Let",
"definitions" : [{"name" : {"id" : "v_r_2986_26_14_55_133_3135093", "type" : {"op" : "Int"}},
"value" : {"op" : "Literal", "type" : {"op" : "Int"}, "value" : 10},
"export_as" : ["v_r_2986_26_14_55_133_313"]}],
"body" : {"op" : "Var", "id" : "v_r_2986_26_14_55_133_3135093", "type" : {"op" : "Int"}}}}}}}}}}},
"else" : {"op" : "Shift",
"label" : {"op" : "Var", "id" : "p_4_71_2444977", "type" : {"op" : "Label"}},
"n" : {"op" : "Literal", "type" : {"op" : "Int"}, "value" : 0},
"k" : {"id" : "k_7_2_125_3055325", "type" : {"op" : "Stack", "resume_return" : {"op" : "Unit"}, "resume_args" : [{"op" : "Bottom"}]}},
"returnType" : {"op" : "Unit"},
"body" : {"op" : "Literal", "type" : {"op" : "Unit"}, "value" : "unit"}}},
"export_as" : ["c_10_5_60_138_318"]}],
"body" : {"op" : "Let",
"definitions" : [{"name" : {"id" : "tmp5252", "type" : {"op" : "Bool"}},
"value" : {"op" : "App", "fn" : {"op" : "Var", "id" : "infixEq72", "type" : {"op" : "Function", "params" : [{"op" : "Int"},
{"op" : "Int"}], "return" : {"op" : "Bool"}, "purity" : "Effectful"}}, "args" : [{"op" : "Var", "id" : "c_10_5_60_138_3184978", "type" : {"op" : "Int"}}, {"op" : "Literal", "type" : {"op" : "Int"}, "value" : 36}]},
"export_as" : ["tmp"]}],
"body" : {"op" : "IfZero",
"cond" : {"op" : "Var", "id" : "tmp5252", "type" : {"op" : "Bool"}},
"then" : {"op" : "Let",
"definitions" : [{"name" : {"id" : "tmp5254", "type" : {"op" : "Bool"}},
"value" : {"op" : "App", "fn" : {"op" : "Var", "id" : "infixEq72", "type" : {"op" : "Function", "params" : [{"op" : "Int"},
{"op" : "Int"}], "return" : {"op" : "Bool"}, "purity" : "Effectful"}}, "args" : [{"op" : "Var", "id" : "c_10_5_60_138_3184978", "type" : {"op" : "Int"}}, {"op" : "Literal", "type" : {"op" : "Int"}, "value" : 10}]},
"export_as" : ["tmp"]}],
"body" : {"op" : "IfZero",
"cond" : {"op" : "Var", "id" : "tmp5254", "type" : {"op" : "Bool"}},
"then" : {"op" : "Shift",
"label" : {"op" : "Var", "id" : "p_4_71_2444977", "type" : {"op" : "Label"}},
"n" : {"op" : "Literal", "type" : {"op" : "Int"}, "value" : 0},
"k" : {"id" : "k_7_2_146_3335326", "type" : {"op" : "Stack", "resume_return" : {"op" : "Unit"}, "resume_args" : [{"op" : "Bottom"}]}},
"returnType" : {"op" : "Unit"},
"body" : {"op" : "Literal", "type" : {"op" : "Unit"}, "value" : "unit"}},
"else" : {"op" : "Let",
"definitions" : [{"name" : {"id" : "v_r_2962_13_6_3285105", "type" : {"op" : "Int"}},
"value" : {"op" : "Load", "ref" : {"op" : "Var", "id" : "s_4_1505016", "type" : {"op" : "Ref", "to" : {"op" : "Int"}}}},
"export_as" : ["v_r_2962_13_6_328"]}],
"body" : {"op" : "Let",
"definitions" : [{"name" : {"id" : "tmp5255", "type" : {"op" : "Int"}},
"value" : {"op" : "App", "fn" : {"op" : "Var", "id" : "infixAdd96", "type" : {"op" : "Function", "params" : [{"op" : "Int"},
{"op" : "Int"}], "return" : {"op" : "Int"}, "purity" : "Effectful"}}, "args" : [{"op" : "Var", "id" : "v_r_2962_13_6_3285105", "type" : {"op" : "Int"}}, {"op" : "Var", "id" : "a_9_4_41_117_2975031", "type" : {"op" : "Int"}}]},
"export_as" : ["tmp"]}],
"body" : {"op" : "Let",
"definitions" : [{"name" : {"id" : "__15_8_3305169", "type" : {"op" : "Unit"}},
"value" : {"op" : "Store", "ref" : {"op" : "Var", "id" : "s_4_1505016", "type" : {"op" : "Ref", "to" : {"op" : "Int"}}}, "value" : {"op" : "Var", "id" : "tmp5255", "type" : {"op" : "Int"}}},
"export_as" : ["__15_8_330"]}],
"body" : {"op" : "App", "fn" : {"op" : "Var", "id" : "parse_worker_8_3_40_116_2964906", "type" : {"op" : "Function", "params" : [{"op" : "Int"}], "return" : {"op" : "Unit"}, "purity" : "Effectful"}}, "args" : [{"op" : "Literal", "type" : {"op" : "Int"}, "value" : 0}]}}}}}},
"else" : {"op" : "Let",
"definitions" : [{"name" : {"id" : "tmp5253", "type" : {"op" : "Int"}},
"value" : {"op" : "App", "fn" : {"op" : "Var", "id" : "infixAdd96", "type" : {"op" : "Function", "params" : [{"op" : "Int"},
{"op" : "Int"}], "return" : {"op" : "Int"}, "purity" : "Effectful"}}, "args" : [{"op" : "Var", "id" : "a_9_4_41_117_2975031", "type" : {"op" : "Int"}}, {"op" : "Literal", "type" : {"op" : "Int"}, "value" : 1}]},
"export_as" : ["tmp"]}],
"body" : {"op" : "App", "fn" : {"op" : "Var", "id" : "parse_worker_8_3_40_116_2964906", "type" : {"op" : "Function", "params" : [{"op" : "Int"}], "return" : {"op" : "Unit"}, "purity" : "Effectful"}}, "args" : [{"op" : "Var", "id" : "tmp5253", "type" : {"op" : "Int"}}]}}}}}}}},
"export_as" : ["parse_worker_8_3_40_116_296"]}],
"body" : {"op" : "App", "fn" : {"op" : "Var", "id" : "parse_worker_8_3_40_116_2964906", "type" : {"op" : "Function", "params" : [{"op" : "Int"}], "return" : {"op" : "Unit"}, "purity" : "Effectful"}}, "args" : [{"op" : "Literal", "type" : {"op" : "Int"}, "value" : 0}]}}},
"return" : {"params" : [{"id" : "v_tmp_52915327", "type" : {"op" : "Unit"}}],
"body" : {"op" : "Var", "id" : "v_tmp_52915327", "type" : {"op" : "Unit"}}}}}},
"return" : {"params" : [{"id" : "v_tmp_52895328", "type" : {"op" : "Unit"}}],
"body" : {"op" : "Var", "id" : "v_tmp_52895328", "type" : {"op" : "Unit"}}}}},
"return" : {"params" : [{"id" : "v_tmp_52865329", "type" : {"op" : "Unit"}}],
"body" : {"op" : "Var", "id" : "v_tmp_52865329", "type" : {"op" : "Unit"}}}}},
"export_as" : ["__16_334"]}],
"body" : {"op" : "Load", "ref" : {"op" : "Var", "id" : "s_4_1505016", "type" : {"op" : "Ref", "to" : {"op" : "Int"}}}}}},
"return" : {"params" : [{"id" : "v_tmp_52855330", "type" : {"op" : "Int"}}],
"body" : {"op" : "Var", "id" : "v_tmp_52855330", "type" : {"op" : "Int"}}}},
"export_as" : ["r"]}],
"body" : {"op" : "Let",
"definitions" : [{"name" : {"id" : "tmp5261", "type" : {"op" : "String"}},
"value" : {"op" : "App", "fn" : {"op" : "Var", "id" : "show14", "type" : {"op" : "Function", "params" : [{"op" : "Int"}], "return" : {"op" : "String"}, "purity" : "Effectful"}}, "args" : [{"op" : "Var", "id" : "r2851", "type" : {"op" : "Int"}}]},
"export_as" : ["tmp"]}],
"body" : {"op" : "Let",
"definitions" : [{"name" : {"id" : "tmp5256", "type" : {"op" : "Unit"}},
"value" : {"op" : "App", "fn" : {"op" : "Var", "id" : "println1", "type" : {"op" : "Function", "params" : [{"op" : "String"}], "return" : {"op" : "Unit"}, "purity" : "Effectful"}}, "args" : [{"op" : "Var", "id" : "tmp5261", "type" : {"op" : "String"}}]},
"export_as" : ["tmp"]}],
"body" : {"op" : "Var", "id" : "tmp5256", "type" : {"op" : "Unit"}}}}}}}},
"export_as" : ["main"]}],
"main" : {"op" : "App", "fn" : {"op" : "Var", "id" : "main2837", "type" : {"op" : "Function", "params" : [], "return" : {"op" : "Unit"}, "purity" : "Effectful"}}, "args" : []}}