{"definitions" : [{"name" : {"id" : "println1", "type" : {"op" : "Function", "params" : [{"op" : "String"}], "return" : {"op" : "Unit"}, "purity" : "Effectful"}},
"value" : {"op" : "Abs",
"params" : [{"id" : "value2", "type" : {"op" : "String"}}],
"body" : {"op" : "Primitive",
"name" : "println(String): Unit",
"args" : [{"op" : "Var", "id" : "value2", "type" : {"op" : "String"}}],
"returns" : [{"id" : "v_tmp_44664489", "type" : {"op" : "Unit"}}],
"rest" : {"op" : "Var", "id" : "v_tmp_44664489", "type" : {"op" : "Unit"}}}},
"export_as" : ["println"]},
{"name" : {"id" : "show14", "type" : {"op" : "Function", "params" : [{"op" : "Int"}], "return" : {"op" : "String"}, "purity" : "Pure"}},
"value" : {"op" : "Abs",
"params" : [{"id" : "value13", "type" : {"op" : "Int"}}],
"body" : {"op" : "Primitive",
"name" : "show(Int): String",
"args" : [{"op" : "Var", "id" : "value13", "type" : {"op" : "Int"}}],
"returns" : [{"id" : "v_tmp_44674490", "type" : {"op" : "String"}}],
"rest" : {"op" : "Var", "id" : "v_tmp_44674490", "type" : {"op" : "String"}}}},
"export_as" : ["show"]},
{"name" : {"id" : "infixConcat35", "type" : {"op" : "Function", "params" : [{"op" : "String"},
{"op" : "String"}], "return" : {"op" : "String"}, "purity" : "Pure"}},
"value" : {"op" : "Abs",
"params" : [{"id" : "s133", "type" : {"op" : "String"}}, {"id" : "s234", "type" : {"op" : "String"}}],
"body" : {"op" : "Primitive",
"name" : "infixConcat(String, String): String",
"args" : [{"op" : "Var", "id" : "s133", "type" : {"op" : "String"}}, {"op" : "Var", "id" : "s234", "type" : {"op" : "String"}}],
"returns" : [{"id" : "v_tmp_44684491", "type" : {"op" : "String"}}],
"rest" : {"op" : "Var", "id" : "v_tmp_44684491", "type" : {"op" : "String"}}}},
"export_as" : ["infixConcat"]},
{"name" : {"id" : "length37", "type" : {"op" : "Function", "params" : [{"op" : "String"}], "return" : {"op" : "Int"}, "purity" : "Pure"}},
"value" : {"op" : "Abs",
"params" : [{"id" : "str36", "type" : {"op" : "String"}}],
"body" : {"op" : "Primitive",
"name" : "length(String): Int",
"args" : [{"op" : "Var", "id" : "str36", "type" : {"op" : "String"}}],
"returns" : [{"id" : "v_tmp_44694492", "type" : {"op" : "Int"}}],
"rest" : {"op" : "Var", "id" : "v_tmp_44694492", "type" : {"op" : "Int"}}}},
"export_as" : ["length"]},
{"name" : {"id" : "infixEq72", "type" : {"op" : "Function", "params" : [{"op" : "Int"},
{"op" : "Int"}], "return" : {"op" : "Bool"}, "purity" : "Pure"}},
"value" : {"op" : "Abs",
"params" : [{"id" : "x70", "type" : {"op" : "Int"}}, {"id" : "y71", "type" : {"op" : "Int"}}],
"body" : {"op" : "Primitive",
"name" : "infixEq(Int, Int): Boolean",
"args" : [{"op" : "Var", "id" : "x70", "type" : {"op" : "Int"}}, {"op" : "Var", "id" : "y71", "type" : {"op" : "Int"}}],
"returns" : [{"id" : "v_tmp_44704493", "type" : {"op" : "Bool"}}],
"rest" : {"op" : "Var", "id" : "v_tmp_44704493", "type" : {"op" : "Bool"}}}},
"export_as" : ["infixEq"]},
{"name" : {"id" : "infixEq78", "type" : {"op" : "Function", "params" : [{"op" : "String"},
{"op" : "String"}], "return" : {"op" : "Bool"}, "purity" : "Pure"}},
"value" : {"op" : "Abs",
"params" : [{"id" : "x76", "type" : {"op" : "String"}}, {"id" : "y77", "type" : {"op" : "String"}}],
"body" : {"op" : "Primitive",
"name" : "infixEq(String, String): Boolean",
"args" : [{"op" : "Var", "id" : "x76", "type" : {"op" : "String"}}, {"op" : "Var", "id" : "y77", "type" : {"op" : "String"}}],
"returns" : [{"id" : "v_tmp_44714494", "type" : {"op" : "Bool"}}],
"rest" : {"op" : "Var", "id" : "v_tmp_44714494", "type" : {"op" : "Bool"}}}},
"export_as" : ["infixEq"]},
{"name" : {"id" : "infixAdd96", "type" : {"op" : "Function", "params" : [{"op" : "Int"},
{"op" : "Int"}], "return" : {"op" : "Int"}, "purity" : "Pure"}},
"value" : {"op" : "Abs",
"params" : [{"id" : "x94", "type" : {"op" : "Int"}}, {"id" : "y95", "type" : {"op" : "Int"}}],
"body" : {"op" : "Primitive",
"name" : "infixAdd(Int, Int): Int",
"args" : [{"op" : "Var", "id" : "x94", "type" : {"op" : "Int"}}, {"op" : "Var", "id" : "y95", "type" : {"op" : "Int"}}],
"returns" : [{"id" : "v_tmp_44724495", "type" : {"op" : "Int"}}],
"rest" : {"op" : "Var", "id" : "v_tmp_44724495", "type" : {"op" : "Int"}}}},
"export_as" : ["infixAdd"]},
{"name" : {"id" : "infixMul99", "type" : {"op" : "Function", "params" : [{"op" : "Int"},
{"op" : "Int"}], "return" : {"op" : "Int"}, "purity" : "Pure"}},
"value" : {"op" : "Abs",
"params" : [{"id" : "x97", "type" : {"op" : "Int"}}, {"id" : "y98", "type" : {"op" : "Int"}}],
"body" : {"op" : "Primitive",
"name" : "infixMul(Int, Int): Int",
"args" : [{"op" : "Var", "id" : "x97", "type" : {"op" : "Int"}}, {"op" : "Var", "id" : "y98", "type" : {"op" : "Int"}}],
"returns" : [{"id" : "v_tmp_44734496", "type" : {"op" : "Int"}}],
"rest" : {"op" : "Var", "id" : "v_tmp_44734496", "type" : {"op" : "Int"}}}},
"export_as" : ["infixMul"]},
{"name" : {"id" : "infixSub105", "type" : {"op" : "Function", "params" : [{"op" : "Int"},
{"op" : "Int"}], "return" : {"op" : "Int"}, "purity" : "Pure"}},
"value" : {"op" : "Abs",
"params" : [{"id" : "x103", "type" : {"op" : "Int"}}, {"id" : "y104", "type" : {"op" : "Int"}}],
"body" : {"op" : "Primitive",
"name" : "infixSub(Int, Int): Int",
"args" : [{"op" : "Var", "id" : "x103", "type" : {"op" : "Int"}}, {"op" : "Var", "id" : "y104", "type" : {"op" : "Int"}}],
"returns" : [{"id" : "v_tmp_44744497", "type" : {"op" : "Int"}}],
"rest" : {"op" : "Var", "id" : "v_tmp_44744497", "type" : {"op" : "Int"}}}},
"export_as" : ["infixSub"]},
{"name" : {"id" : "infixLt178", "type" : {"op" : "Function", "params" : [{"op" : "Int"},
{"op" : "Int"}], "return" : {"op" : "Bool"}, "purity" : "Pure"}},
"value" : {"op" : "Abs",
"params" : [{"id" : "x176", "type" : {"op" : "Int"}}, {"id" : "y177", "type" : {"op" : "Int"}}],
"body" : {"op" : "Primitive",
"name" : "infixLt(Int, Int): Boolean",
"args" : [{"op" : "Var", "id" : "x176", "type" : {"op" : "Int"}}, {"op" : "Var", "id" : "y177", "type" : {"op" : "Int"}}],
"returns" : [{"id" : "v_tmp_44754498", "type" : {"op" : "Bool"}}],
"rest" : {"op" : "Var", "id" : "v_tmp_44754498", "type" : {"op" : "Bool"}}}},
"export_as" : ["infixLt"]},
{"name" : {"id" : "infixGte187", "type" : {"op" : "Function", "params" : [{"op" : "Int"},
{"op" : "Int"}], "return" : {"op" : "Bool"}, "purity" : "Pure"}},
"value" : {"op" : "Abs",
"params" : [{"id" : "x185", "type" : {"op" : "Int"}}, {"id" : "y186", "type" : {"op" : "Int"}}],
"body" : {"op" : "Primitive",
"name" : "infixGte(Int, Int): Boolean",
"args" : [{"op" : "Var", "id" : "x185", "type" : {"op" : "Int"}}, {"op" : "Var", "id" : "y186", "type" : {"op" : "Int"}}],
"returns" : [{"id" : "v_tmp_44764499", "type" : {"op" : "Bool"}}],
"rest" : {"op" : "Var", "id" : "v_tmp_44764499", "type" : {"op" : "Bool"}}}},
"export_as" : ["infixGte"]},
{"name" : {"id" : "toInt2452", "type" : {"op" : "Function", "params" : [{"op" : "String"}], "return" : {"op" : "Int"}, "purity" : "Pure"}},
"value" : {"op" : "Abs",
"params" : [{"id" : "ch2451", "type" : {"op" : "String"}}],
"body" : {"op" : "Primitive",
"name" : "charCode(String): Int",
"args" : [{"op" : "Var", "id" : "ch2451", "type" : {"op" : "String"}}],
"returns" : [{"id" : "v_tmp_44774500", "type" : {"op" : "Int"}}],
"rest" : {"op" : "Var", "id" : "v_tmp_44774500", "type" : {"op" : "Int"}}}},
"export_as" : ["toInt"]},
{"name" : {"id" : "infixLte2460", "type" : {"op" : "Function", "params" : [{"op" : "String"},
{"op" : "String"}], "return" : {"op" : "Bool"}, "purity" : "Pure"}},
"value" : {"op" : "Abs",
"params" : [{"id" : "x2458", "type" : {"op" : "String"}}, {"id" : "y2459", "type" : {"op" : "String"}}],
"body" : {"op" : "Primitive",
"name" : "infixLte(String, String): Boolean",
"args" : [{"op" : "Var", "id" : "x2458", "type" : {"op" : "String"}}, {"op" : "Var", "id" : "y2459", "type" : {"op" : "String"}}],
"returns" : [{"id" : "v_tmp_44784501", "type" : {"op" : "Bool"}}],
"rest" : {"op" : "Var", "id" : "v_tmp_44784501", "type" : {"op" : "Bool"}}}},
"export_as" : ["infixLte"]},
{"name" : {"id" : "infixGte2466", "type" : {"op" : "Function", "params" : [{"op" : "String"},
{"op" : "String"}], "return" : {"op" : "Bool"}, "purity" : "Pure"}},
"value" : {"op" : "Abs",
"params" : [{"id" : "x2464", "type" : {"op" : "String"}}, {"id" : "y2465", "type" : {"op" : "String"}}],
"body" : {"op" : "Primitive",
"name" : "infixGte(String, String): Boolean",
"args" : [{"op" : "Var", "id" : "x2464", "type" : {"op" : "String"}}, {"op" : "Var", "id" : "y2465", "type" : {"op" : "String"}}],
"returns" : [{"id" : "v_tmp_44794502", "type" : {"op" : "Bool"}}],
"rest" : {"op" : "Var", "id" : "v_tmp_44794502", "type" : {"op" : "Bool"}}}},
"export_as" : ["infixGte"]},
{"name" : {"id" : "unsafeCharAt2478", "type" : {"op" : "Function", "params" : [{"op" : "String"},
{"op" : "Int"}], "return" : {"op" : "String"}, "purity" : "Pure"}},
"value" : {"op" : "Abs",
"params" : [{"id" : "str2476", "type" : {"op" : "String"}}, {"id" : "n2477", "type" : {"op" : "Int"}}],
"body" : {"op" : "Primitive",
"name" : "!sexp:(\"charAt(Int, String): String\" $arg1:int $arg0:str)",
"args" : [{"op" : "Var", "id" : "str2476", "type" : {"op" : "String"}}, {"op" : "Var", "id" : "n2477", "type" : {"op" : "Int"}}],
"returns" : [{"id" : "v_tmp_44804503", "type" : {"op" : "String"}}],
"rest" : {"op" : "Var", "id" : "v_tmp_44804503", "type" : {"op" : "String"}}}},
"export_as" : ["unsafeCharAt"]},
{"name" : {"id" : "argCount2767", "type" : {"op" : "Function", "params" : [], "return" : {"op" : "Int"}, "purity" : "Effectful"}},
"value" : {"op" : "Abs",
"params" : [],
"body" : {"op" : "Primitive",
"name" : "get_argc(): Int",
"args" : [],
"returns" : [{"id" : "v_tmp_44814504", "type" : {"op" : "Int"}}],
"rest" : {"op" : "Var", "id" : "v_tmp_44814504", "type" : {"op" : "Int"}}}},
"export_as" : ["argCount"]},
{"name" : {"id" : "argument2769", "type" : {"op" : "Function", "params" : [{"op" : "Int"}], "return" : {"op" : "String"}, "purity" : "Effectful"}},
"value" : {"op" : "Abs",
"params" : [{"id" : "i2768", "type" : {"op" : "Int"}}],
"body" : {"op" : "Primitive",
"name" : "get_arg(Int): String",
"args" : [{"op" : "Var", "id" : "i2768", "type" : {"op" : "Int"}}],
"returns" : [{"id" : "v_tmp_44824505", "type" : {"op" : "String"}}],
"rest" : {"op" : "Var", "id" : "v_tmp_44824505", "type" : {"op" : "String"}}}},
"export_as" : ["argument"]},
{"name" : {"id" : "charAt2475", "type" : {"op" : "Function", "params" : [{"op" : "String"},
{"op" : "Int"},
{"op" : "Codata", "interface_tag" : "Exception532", "methods" : [{"tag" : "raise602", "params" : [{"op" : "Top"}, {"op" : "String"}], "return" : {"op" : "Bottom"}}]}], "return" : {"op" : "String"}, "purity" : "Effectful"}},
"value" : {"op" : "Abs",
"params" : [{"id" : "str2473", "type" : {"op" : "String"}}, {"id" : "index2474", "type" : {"op" : "Int"}}, {"id" : "Exception2728", "type" : {"op" : "Codata", "interface_tag" : "Exception532", "methods" : [{"tag" : "raise602", "params" : [{"op" : "Top"}, {"op" : "String"}], "return" : {"op" : "Bottom"}}]}}],
"body" : {"op" : "Let",
"definitions" : [{"name" : {"id" : "tmp4463", "type" : {"op" : "Bool"}},
"value" : {"op" : "App", "fn" : {"op" : "Var", "id" : "infixLt178", "type" : {"op" : "Function", "params" : [{"op" : "Int"},
{"op" : "Int"}], "return" : {"op" : "Bool"}, "purity" : "Effectful"}}, "args" : [{"op" : "Var", "id" : "index2474", "type" : {"op" : "Int"}}, {"op" : "Literal", "type" : {"op" : "Int"}, "value" : 0}]},
"export_as" : ["tmp"]}],
"body" : {"op" : "Let",
"definitions" : [{"name" : {"id" : "v_r_30613890", "type" : {"op" : "Bool"}},
"value" : {"op" : "IfZero",
"cond" : {"op" : "Var", "id" : "tmp4463", "type" : {"op" : "Bool"}},
"then" : {"op" : "Let",
"definitions" : [{"name" : {"id" : "tmp4431", "type" : {"op" : "Int"}},
"value" : {"op" : "App", "fn" : {"op" : "Var", "id" : "length37", "type" : {"op" : "Function", "params" : [{"op" : "String"}], "return" : {"op" : "Int"}, "purity" : "Effectful"}}, "args" : [{"op" : "Var", "id" : "str2473", "type" : {"op" : "String"}}]},
"export_as" : ["tmp"]}],
"body" : {"op" : "Let",
"definitions" : [{"name" : {"id" : "tmp4432", "type" : {"op" : "Bool"}},
"value" : {"op" : "App", "fn" : {"op" : "Var", "id" : "infixGte187", "type" : {"op" : "Function", "params" : [{"op" : "Int"},
{"op" : "Int"}], "return" : {"op" : "Bool"}, "purity" : "Effectful"}}, "args" : [{"op" : "Var", "id" : "index2474", "type" : {"op" : "Int"}}, {"op" : "Var", "id" : "tmp4431", "type" : {"op" : "Int"}}]},
"export_as" : ["tmp"]}],
"body" : {"op" : "Var", "id" : "tmp4432", "type" : {"op" : "Bool"}}}},
"else" : {"op" : "Literal", "type" : {"op" : "Bool"}, "value" : true}},
"export_as" : ["v_r_3061"]}],
"body" : {"op" : "IfZero",
"cond" : {"op" : "Var", "id" : "v_r_30613890", "type" : {"op" : "Bool"}},
"then" : {"op" : "Let",
"definitions" : [{"name" : {"id" : "tmp4439", "type" : {"op" : "String"}},
"value" : {"op" : "App", "fn" : {"op" : "Var", "id" : "unsafeCharAt2478", "type" : {"op" : "Function", "params" : [{"op" : "String"},
{"op" : "Int"}], "return" : {"op" : "String"}, "purity" : "Effectful"}}, "args" : [{"op" : "Var", "id" : "str2473", "type" : {"op" : "String"}}, {"op" : "Var", "id" : "index2474", "type" : {"op" : "Int"}}]},
"export_as" : ["tmp"]}],
"body" : {"op" : "Var", "id" : "tmp4439", "type" : {"op" : "String"}}},
"else" : {"op" : "Let",
"definitions" : [{"name" : {"id" : "tmp4433", "type" : {"op" : "Data", "type_tag" : "OutOfBounds541", "constructors" : [{"tag" : "OutOfBounds604", "fields" : []}]}},
"value" : {"op" : "The",
"type" : {"op" : "Data", "type_tag" : "OutOfBounds541", "constructors" : [{"tag" : "OutOfBounds604", "fields" : []}]},
"term" : {"op" : "Construct", "type_tag" : "OutOfBounds541", "tag" : "OutOfBounds604", "args" : []}},
"export_as" : ["tmp"]}],
"body" : {"op" : "Let",
"definitions" : [{"name" : {"id" : "tmp4434", "type" : {"op" : "String"}},
"value" : {"op" : "App", "fn" : {"op" : "Var", "id" : "show14", "type" : {"op" : "Function", "params" : [{"op" : "Int"}], "return" : {"op" : "String"}, "purity" : "Effectful"}}, "args" : [{"op" : "Var", "id" : "index2474", "type" : {"op" : "Int"}}]},
"export_as" : ["tmp"]}],
"body" : {"op" : "Let",
"definitions" : [{"name" : {"id" : "tmp4435", "type" : {"op" : "String"}},
"value" : {"op" : "App", "fn" : {"op" : "Var", "id" : "infixConcat35", "type" : {"op" : "Function", "params" : [{"op" : "String"},
{"op" : "String"}], "return" : {"op" : "String"}, "purity" : "Effectful"}}, "args" : [{"op" : "Literal", "type" : {"op" : "String"}, "value" : "Index out of bounds: "}, {"op" : "Var", "id" : "tmp4434", "type" : {"op" : "String"}}]},
"export_as" : ["tmp"]}],
"body" : {"op" : "Let",
"definitions" : [{"name" : {"id" : "tmp4436", "type" : {"op" : "String"}},
"value" : {"op" : "App", "fn" : {"op" : "Var", "id" : "infixConcat35", "type" : {"op" : "Function", "params" : [{"op" : "String"},
{"op" : "String"}], "return" : {"op" : "String"}, "purity" : "Effectful"}}, "args" : [{"op" : "Var", "id" : "tmp4435", "type" : {"op" : "String"}}, {"op" : "Literal", "type" : {"op" : "String"}, "value" : " in string: '"}]},
"export_as" : ["tmp"]}],
"body" : {"op" : "Let",
"definitions" : [{"name" : {"id" : "tmp4437", "type" : {"op" : "String"}},
"value" : {"op" : "App", "fn" : {"op" : "Var", "id" : "infixConcat35", "type" : {"op" : "Function", "params" : [{"op" : "String"},
{"op" : "String"}], "return" : {"op" : "String"}, "purity" : "Effectful"}}, "args" : [{"op" : "Var", "id" : "tmp4436", "type" : {"op" : "String"}}, {"op" : "Var", "id" : "str2473", "type" : {"op" : "String"}}]},
"export_as" : ["tmp"]}],
"body" : {"op" : "Let",
"definitions" : [{"name" : {"id" : "tmp4438", "type" : {"op" : "String"}},
"value" : {"op" : "App", "fn" : {"op" : "Var", "id" : "infixConcat35", "type" : {"op" : "Function", "params" : [{"op" : "String"},
{"op" : "String"}], "return" : {"op" : "String"}, "purity" : "Effectful"}}, "args" : [{"op" : "Var", "id" : "tmp4437", "type" : {"op" : "String"}}, {"op" : "Literal", "type" : {"op" : "String"}, "value" : "'"}]},
"export_as" : ["tmp"]}],
"body" : {"op" : "Invoke", "receiver" : {"op" : "Var", "id" : "Exception2728", "type" : {"op" : "Codata", "interface_tag" : "Exception532", "methods" : [{"tag" : "raise602", "params" : [{"op" : "Top"}, {"op" : "String"}], "return" : {"op" : "Bottom"}}]}}, "ifce_tag" : "Exception532", "tag" : "raise602", "args" : [{"op" : "Var", "id" : "tmp4433", "type" : {"op" : "Data", "type_tag" : "OutOfBounds541", "constructors" : [{"tag" : "OutOfBounds604", "fields" : []}]}}, {"op" : "Var", "id" : "tmp4438", "type" : {"op" : "String"}}]}}}}}}}}}}},
"export_as" : ["charAt"]},
{"name" : {"id" : "main2821", "type" : {"op" : "Function", "params" : [], "return" : {"op" : "Unit"}, "purity" : "Effectful"}},
"value" : {"op" : "Abs",
"params" : [],
"body" : {"op" : "Let",
"definitions" : [{"name" : {"id" : "n2830", "type" : {"op" : "Int"}},
"value" : {"op" : "Let",
"definitions" : [{"name" : {"id" : "p_8_94236", "type" : {"op" : "Label"}},
"value" : {"op" : "FreshLabel"},
"export_as" : ["p_8_9"]}],
"body" : {"op" : "Reset",
"label" : {"op" : "Var", "id" : "p_8_94236", "type" : {"op" : "Label"}},
"region" : {"id" : "v_tmp_44844506", "type" : {"op" : "Ptr"}},
"body" : {"op" : "LetRec",
"definitions" : [{"name" : {"id" : "toList_1_1_34317", "type" : {"op" : "Function", "params" : [{"op" : "Int"},
{"op" : "Data", "type_tag" : "List916", "constructors" : [{"tag" : "Nil1153", "fields" : []}, {"tag" : "Cons1154", "fields" : [{"op" : "Top"}, {"op" : "Data", "type_tag" : "List916", "constructors" : [{"tag" : "Nil1153", "fields" : []}, {"tag" : "Cons1154", "fields" : [{"op" : "Top"}, {"op" : "Ptr"}]}]}]}]}], "return" : {"op" : "Data", "type_tag" : "List916", "constructors" : [{"tag" : "Nil1153", "fields" : []}, {"tag" : "Cons1154", "fields" : [{"op" : "Top"}, {"op" : "Data", "type_tag" : "List916", "constructors" : [{"tag" : "Nil1153", "fields" : []}, {"tag" : "Cons1154", "fields" : [{"op" : "Top"}, {"op" : "Ptr"}]}]}]}]}, "purity" : "Effectful"}},
"value" : {"op" : "Abs",
"params" : [{"id" : "start_2_2_44332", "type" : {"op" : "Int"}}, {"id" : "acc_3_3_54272", "type" : {"op" : "Data", "type_tag" : "List916", "constructors" : [{"tag" : "Nil1153", "fields" : []}, {"tag" : "Cons1154", "fields" : [{"op" : "Top"}, {"op" : "Data", "type_tag" : "List916", "constructors" : [{"tag" : "Nil1153", "fields" : []}, {"tag" : "Cons1154", "fields" : [{"op" : "Top"}, {"op" : "Ptr"}]}]}]}]}}],
"body" : {"op" : "Let",
"definitions" : [{"name" : {"id" : "tmp4462", "type" : {"op" : "Bool"}},
"value" : {"op" : "App", "fn" : {"op" : "Var", "id" : "infixLt178", "type" : {"op" : "Function", "params" : [{"op" : "Int"},
{"op" : "Int"}], "return" : {"op" : "Bool"}, "purity" : "Effectful"}}, "args" : [{"op" : "Var", "id" : "start_2_2_44332", "type" : {"op" : "Int"}}, {"op" : "Literal", "type" : {"op" : "Int"}, "value" : 0}]},
"export_as" : ["tmp"]}],
"body" : {"op" : "IfZero",
"cond" : {"op" : "Var", "id" : "tmp4462", "type" : {"op" : "Bool"}},
"then" : {"op" : "Let",
"definitions" : [{"name" : {"id" : "tmp4440", "type" : {"op" : "String"}},
"value" : {"op" : "App", "fn" : {"op" : "Var", "id" : "argument2769", "type" : {"op" : "Function", "params" : [{"op" : "Int"}], "return" : {"op" : "String"}, "purity" : "Effectful"}}, "args" : [{"op" : "Var", "id" : "start_2_2_44332", "type" : {"op" : "Int"}}]},
"export_as" : ["tmp"]}],
"body" : {"op" : "Let",
"definitions" : [{"name" : {"id" : "tmp4441", "type" : {"op" : "Int"}},
"value" : {"op" : "App", "fn" : {"op" : "Var", "id" : "infixSub105", "type" : {"op" : "Function", "params" : [{"op" : "Int"},
{"op" : "Int"}], "return" : {"op" : "Int"}, "purity" : "Effectful"}}, "args" : [{"op" : "Var", "id" : "start_2_2_44332", "type" : {"op" : "Int"}}, {"op" : "Literal", "type" : {"op" : "Int"}, "value" : 1}]},
"export_as" : ["tmp"]}],
"body" : {"op" : "Let",
"definitions" : [{"name" : {"id" : "tmp4442", "type" : {"op" : "Data", "type_tag" : "List916", "constructors" : [{"tag" : "Nil1153", "fields" : []}, {"tag" : "Cons1154", "fields" : [{"op" : "Top"}, {"op" : "Data", "type_tag" : "List916", "constructors" : [{"tag" : "Nil1153", "fields" : []}, {"tag" : "Cons1154", "fields" : [{"op" : "Top"}, {"op" : "Ptr"}]}]}]}]}},
"value" : {"op" : "The",
"type" : {"op" : "Data", "type_tag" : "List916", "constructors" : [{"tag" : "Nil1153", "fields" : []}, {"tag" : "Cons1154", "fields" : [{"op" : "Top"}, {"op" : "Data", "type_tag" : "List916", "constructors" : [{"tag" : "Nil1153", "fields" : []}, {"tag" : "Cons1154", "fields" : [{"op" : "Top"}, {"op" : "Ptr"}]}]}]}]},
"term" : {"op" : "Construct", "type_tag" : "List916", "tag" : "Cons1154", "args" : [{"op" : "Var", "id" : "tmp4440", "type" : {"op" : "String"}}, {"op" : "Var", "id" : "acc_3_3_54272", "type" : {"op" : "Data", "type_tag" : "List916", "constructors" : [{"tag" : "Nil1153", "fields" : []}, {"tag" : "Cons1154", "fields" : [{"op" : "Top"}, {"op" : "Data", "type_tag" : "List916", "constructors" : [{"tag" : "Nil1153", "fields" : []}, {"tag" : "Cons1154", "fields" : [{"op" : "Top"}, {"op" : "Ptr"}]}]}]}]}}]}},
"export_as" : ["tmp"]}],
"body" : {"op" : "App", "fn" : {"op" : "Var", "id" : "toList_1_1_34317", "type" : {"op" : "Function", "params" : [{"op" : "Int"},
{"op" : "Data", "type_tag" : "List916", "constructors" : [{"tag" : "Nil1153", "fields" : []}, {"tag" : "Cons1154", "fields" : [{"op" : "Top"}, {"op" : "Data", "type_tag" : "List916", "constructors" : [{"tag" : "Nil1153", "fields" : []}, {"tag" : "Cons1154", "fields" : [{"op" : "Top"}, {"op" : "Ptr"}]}]}]}]}], "return" : {"op" : "Data", "type_tag" : "List916", "constructors" : [{"tag" : "Nil1153", "fields" : []}, {"tag" : "Cons1154", "fields" : [{"op" : "Top"}, {"op" : "Data", "type_tag" : "List916", "constructors" : [{"tag" : "Nil1153", "fields" : []}, {"tag" : "Cons1154", "fields" : [{"op" : "Top"}, {"op" : "Ptr"}]}]}]}]}, "purity" : "Effectful"}}, "args" : [{"op" : "Var", "id" : "tmp4441", "type" : {"op" : "Int"}}, {"op" : "Var", "id" : "tmp4442", "type" : {"op" : "Data", "type_tag" : "List916", "constructors" : [{"tag" : "Nil1153", "fields" : []}, {"tag" : "Cons1154", "fields" : [{"op" : "Top"}, {"op" : "Data", "type_tag" : "List916", "constructors" : [{"tag" : "Nil1153", "fields" : []}, {"tag" : "Cons1154", "fields" : [{"op" : "Top"}, {"op" : "Ptr"}]}]}]}]}}]}}}},
"else" : {"op" : "Var", "id" : "acc_3_3_54272", "type" : {"op" : "Data", "type_tag" : "List916", "constructors" : [{"tag" : "Nil1153", "fields" : []}, {"tag" : "Cons1154", "fields" : [{"op" : "Top"}, {"op" : "Data", "type_tag" : "List916", "constructors" : [{"tag" : "Nil1153", "fields" : []}, {"tag" : "Cons1154", "fields" : [{"op" : "Top"}, {"op" : "Ptr"}]}]}]}]}}}}},
"export_as" : ["toList_1_1_3"]}],
"body" : {"op" : "Let",
"definitions" : [{"name" : {"id" : "tmp4461", "type" : {"op" : "Int"}},
"value" : {"op" : "App", "fn" : {"op" : "Var", "id" : "argCount2767", "type" : {"op" : "Function", "params" : [], "return" : {"op" : "Int"}, "purity" : "Effectful"}}, "args" : []},
"export_as" : ["tmp"]}],
"body" : {"op" : "Let",
"definitions" : [{"name" : {"id" : "tmp4443", "type" : {"op" : "Int"}},
"value" : {"op" : "App", "fn" : {"op" : "Var", "id" : "infixSub105", "type" : {"op" : "Function", "params" : [{"op" : "Int"},
{"op" : "Int"}], "return" : {"op" : "Int"}, "purity" : "Effectful"}}, "args" : [{"op" : "Var", "id" : "tmp4461", "type" : {"op" : "Int"}}, {"op" : "Literal", "type" : {"op" : "Int"}, "value" : 1}]},
"export_as" : ["tmp"]}],
"body" : {"op" : "Let",
"definitions" : [{"name" : {"id" : "tmp4444", "type" : {"op" : "Data", "type_tag" : "List916", "constructors" : [{"tag" : "Nil1153", "fields" : []}, {"tag" : "Cons1154", "fields" : [{"op" : "Top"}, {"op" : "Data", "type_tag" : "List916", "constructors" : [{"tag" : "Nil1153", "fields" : []}, {"tag" : "Cons1154", "fields" : [{"op" : "Top"}, {"op" : "Ptr"}]}]}]}]}},
"value" : {"op" : "The",
"type" : {"op" : "Data", "type_tag" : "List916", "constructors" : [{"tag" : "Nil1153", "fields" : []}, {"tag" : "Cons1154", "fields" : [{"op" : "Top"}, {"op" : "Data", "type_tag" : "List916", "constructors" : [{"tag" : "Nil1153", "fields" : []}, {"tag" : "Cons1154", "fields" : [{"op" : "Top"}, {"op" : "Ptr"}]}]}]}]},
"term" : {"op" : "Construct", "type_tag" : "List916", "tag" : "Nil1153", "args" : []}},
"export_as" : ["tmp"]}],
"body" : {"op" : "Let",
"definitions" : [{"name" : {"id" : "v_r_2894_134263", "type" : {"op" : "Data", "type_tag" : "List916", "constructors" : [{"tag" : "Nil1153", "fields" : []}, {"tag" : "Cons1154", "fields" : [{"op" : "Top"}, {"op" : "Data", "type_tag" : "List916", "constructors" : [{"tag" : "Nil1153", "fields" : []}, {"tag" : "Cons1154", "fields" : [{"op" : "Top"}, {"op" : "Ptr"}]}]}]}]}},
"value" : {"op" : "App", "fn" : {"op" : "Var", "id" : "toList_1_1_34317", "type" : {"op" : "Function", "params" : [{"op" : "Int"},
{"op" : "Data", "type_tag" : "List916", "constructors" : [{"tag" : "Nil1153", "fields" : []}, {"tag" : "Cons1154", "fields" : [{"op" : "Top"}, {"op" : "Data", "type_tag" : "List916", "constructors" : [{"tag" : "Nil1153", "fields" : []}, {"tag" : "Cons1154", "fields" : [{"op" : "Top"}, {"op" : "Ptr"}]}]}]}]}], "return" : {"op" : "Data", "type_tag" : "List916", "constructors" : [{"tag" : "Nil1153", "fields" : []}, {"tag" : "Cons1154", "fields" : [{"op" : "Top"}, {"op" : "Data", "type_tag" : "List916", "constructors" : [{"tag" : "Nil1153", "fields" : []}, {"tag" : "Cons1154", "fields" : [{"op" : "Top"}, {"op" : "Ptr"}]}]}]}]}, "purity" : "Effectful"}}, "args" : [{"op" : "Var", "id" : "tmp4443", "type" : {"op" : "Int"}}, {"op" : "Var", "id" : "tmp4444", "type" : {"op" : "Data", "type_tag" : "List916", "constructors" : [{"tag" : "Nil1153", "fields" : []}, {"tag" : "Cons1154", "fields" : [{"op" : "Top"}, {"op" : "Data", "type_tag" : "List916", "constructors" : [{"tag" : "Nil1153", "fields" : []}, {"tag" : "Cons1154", "fields" : [{"op" : "Top"}, {"op" : "Ptr"}]}]}]}]}}]},
"export_as" : ["v_r_2894_13"]}],
"body" : {"op" : "Let",
"definitions" : [{"name" : {"id" : "v_r_2895_244279", "type" : {"op" : "Data", "type_tag" : "Option749", "constructors" : [{"tag" : "None803", "fields" : []}, {"tag" : "Some804", "fields" : [{"op" : "Top"}]}]}},
"value" : {"op" : "Match",
"scrutinee" : {"op" : "Var", "id" : "v_r_2894_134263", "type" : {"op" : "Data", "type_tag" : "List916", "constructors" : [{"tag" : "Nil1153", "fields" : []}, {"tag" : "Cons1154", "fields" : [{"op" : "Top"}, {"op" : "Data", "type_tag" : "List916", "constructors" : [{"tag" : "Nil1153", "fields" : []}, {"tag" : "Cons1154", "fields" : [{"op" : "Top"}, {"op" : "Ptr"}]}]}]}]}},
"type_tag" : "List916",
"clauses" : [{"tag" : "Nil1153",
"params" : [],
"body" : {"op" : "Let",
"definitions" : [{"name" : {"id" : "tmp4445", "type" : {"op" : "Data", "type_tag" : "Option749", "constructors" : [{"tag" : "None803", "fields" : []}, {"tag" : "Some804", "fields" : [{"op" : "Top"}]}]}},
"value" : {"op" : "The",
"type" : {"op" : "Data", "type_tag" : "Option749", "constructors" : [{"tag" : "None803", "fields" : []}, {"tag" : "Some804", "fields" : [{"op" : "Top"}]}]},
"term" : {"op" : "Construct", "type_tag" : "Option749", "tag" : "None803", "args" : []}},
"export_as" : ["tmp"]}],
"body" : {"op" : "Var", "id" : "tmp4445", "type" : {"op" : "Data", "type_tag" : "Option749", "constructors" : [{"tag" : "None803", "fields" : []}, {"tag" : "Some804", "fields" : [{"op" : "Top"}]}]}}}},
{"tag" : "Cons1154",
"params" : [{"id" : "v_y_3220_10_214325", "type" : {"op" : "String"}}, {"id" : "v_y_3221_11_224260", "type" : {"op" : "Data", "type_tag" : "List916", "constructors" : [{"tag" : "Nil1153", "fields" : []}, {"tag" : "Cons1154", "fields" : [{"op" : "Top"}, {"op" : "Data", "type_tag" : "List916", "constructors" : [{"tag" : "Nil1153", "fields" : []}, {"tag" : "Cons1154", "fields" : [{"op" : "Top"}, {"op" : "Ptr"}]}]}]}]}}],
"body" : {"op" : "Let",
"definitions" : [{"name" : {"id" : "tmp4446", "type" : {"op" : "Data", "type_tag" : "Option749", "constructors" : [{"tag" : "None803", "fields" : []}, {"tag" : "Some804", "fields" : [{"op" : "Top"}]}]}},
"value" : {"op" : "The",
"type" : {"op" : "Data", "type_tag" : "Option749", "constructors" : [{"tag" : "None803", "fields" : []}, {"tag" : "Some804", "fields" : [{"op" : "Top"}]}]},
"term" : {"op" : "Construct", "type_tag" : "Option749", "tag" : "Some804", "args" : [{"op" : "Var", "id" : "v_y_3220_10_214325", "type" : {"op" : "String"}}]}},
"export_as" : ["tmp"]}],
"body" : {"op" : "Var", "id" : "tmp4446", "type" : {"op" : "Data", "type_tag" : "Option749", "constructors" : [{"tag" : "None803", "fields" : []}, {"tag" : "Some804", "fields" : [{"op" : "Top"}]}]}}}}],
"default_clause" : {"params" : [],
"body" : {"op" : "Primitive",
"name" : "non-exhaustive match",
"args" : [],
"returns" : [{"id" : "%bottom", "type" : {"op" : "Bottom"}}],
"rest" : {"op" : "Var", "id" : "%bottom", "type" : {"op" : "Bottom"}}}}},
"export_as" : ["v_r_2895_24"]}],
"body" : {"op" : "Let",
"definitions" : [{"name" : {"id" : "v_r_2896_304257", "type" : {"op" : "String"}},
"value" : {"op" : "Match",
"scrutinee" : {"op" : "Var", "id" : "v_r_2895_244279", "type" : {"op" : "Data", "type_tag" : "Option749", "constructors" : [{"tag" : "None803", "fields" : []}, {"tag" : "Some804", "fields" : [{"op" : "Top"}]}]}},
"type_tag" : "Option749",
"clauses" : [{"tag" : "None803",
"params" : [],
"body" : {"op" : "Literal", "type" : {"op" : "String"}, "value" : ""}},
{"tag" : "Some804",
"params" : [{"id" : "v_y_3711_8_294269", "type" : {"op" : "String"}}],
"body" : {"op" : "Var", "id" : "v_y_3711_8_294269", "type" : {"op" : "String"}}}],
"default_clause" : {"params" : [],
"body" : {"op" : "Primitive",
"name" : "non-exhaustive match",
"args" : [],
"returns" : [{"id" : "%bottom", "type" : {"op" : "Bottom"}}],
"rest" : {"op" : "Var", "id" : "%bottom", "type" : {"op" : "Bottom"}}}}},
"export_as" : ["v_r_2896_30"]}],
"body" : {"op" : "Let",
"definitions" : [{"name" : {"id" : "tmp4447", "type" : {"op" : "Int"}},
"value" : {"op" : "App", "fn" : {"op" : "Var", "id" : "toInt2452", "type" : {"op" : "Function", "params" : [{"op" : "String"}], "return" : {"op" : "Int"}, "purity" : "Effectful"}}, "args" : [{"op" : "Literal", "type" : {"op" : "String"}, "value" : "0"}]},
"export_as" : ["tmp"]}],
"body" : {"op" : "LetRec",
"definitions" : [{"name" : {"id" : "go_6_334326", "type" : {"op" : "Function", "params" : [{"op" : "Int"},
{"op" : "Int"}], "return" : {"op" : "Int"}, "purity" : "Effectful"}},
"value" : {"op" : "Abs",
"params" : [{"id" : "index_7_344292", "type" : {"op" : "Int"}}, {"id" : "acc_8_354252", "type" : {"op" : "Int"}}],
"body" : {"op" : "Let",
"definitions" : [{"name" : {"id" : "v_r_2979_22_494294", "type" : {"op" : "Data", "type_tag" : "Result1949", "constructors" : [{"tag" : "Error1967", "fields" : [{"op" : "Top"}, {"op" : "String"}]}, {"tag" : "Success1972", "fields" : [{"op" : "Top"}]}]}},
"value" : {"op" : "Let",
"definitions" : [{"name" : {"id" : "p_6_13_404278", "type" : {"op" : "Label"}},
"value" : {"op" : "FreshLabel"},
"export_as" : ["p_6_13_40"]}],
"body" : {"op" : "Reset",
"label" : {"op" : "Var", "id" : "p_6_13_404278", "type" : {"op" : "Label"}},
"region" : {"id" : "v_tmp_44864507", "type" : {"op" : "Ptr"}},
"body" : {"op" : "LetRec",
"definitions" : [{"name" : {"id" : "Exception_7_14_414297", "type" : {"op" : "Codata", "interface_tag" : "Exception532", "methods" : [{"tag" : "raise602", "params" : [{"op" : "Top"}, {"op" : "String"}], "return" : {"op" : "Bottom"}}]}},
"value" : {"op" : "New",
"ifce_tag" : "Exception532_Data(OutOfBounds,List())",
"methods" : [{"tag" : "raise602",
"params" : [{"id" : "exc_8_15_424258", "type" : {"op" : "Data", "type_tag" : "OutOfBounds541", "constructors" : [{"tag" : "OutOfBounds604", "fields" : []}]}}, {"id" : "msg_9_16_434312", "type" : {"op" : "String"}}],
"body" : {"op" : "Shift",
"label" : {"op" : "Var", "id" : "p_6_13_404278", "type" : {"op" : "Label"}},
"n" : {"op" : "Literal", "type" : {"op" : "Int"}, "value" : 0},
"k" : {"id" : "k_11_18_454344", "type" : {"op" : "Stack", "resume_return" : {"op" : "Data", "type_tag" : "Result1949", "constructors" : [{"tag" : "Error1967", "fields" : [{"op" : "Top"}, {"op" : "String"}]}, {"tag" : "Success1972", "fields" : [{"op" : "Top"}]}]}, "resume_args" : [{"op" : "Bottom"}]}},
"returnType" : {"op" : "Data", "type_tag" : "Result1949", "constructors" : [{"tag" : "Error1967", "fields" : [{"op" : "Top"}, {"op" : "String"}]}, {"tag" : "Success1972", "fields" : [{"op" : "Top"}]}]},
"body" : {"op" : "Let",
"definitions" : [{"name" : {"id" : "tmp4448", "type" : {"op" : "Data", "type_tag" : "Result1949", "constructors" : [{"tag" : "Error1967", "fields" : [{"op" : "Top"}, {"op" : "String"}]}, {"tag" : "Success1972", "fields" : [{"op" : "Top"}]}]}},
"value" : {"op" : "The",
"type" : {"op" : "Data", "type_tag" : "Result1949", "constructors" : [{"tag" : "Error1967", "fields" : [{"op" : "Top"}, {"op" : "String"}]}, {"tag" : "Success1972", "fields" : [{"op" : "Top"}]}]},
"term" : {"op" : "Construct", "type_tag" : "Result1949", "tag" : "Error1967", "args" : [{"op" : "Var", "id" : "exc_8_15_424258", "type" : {"op" : "Data", "type_tag" : "OutOfBounds541", "constructors" : [{"tag" : "OutOfBounds604", "fields" : []}]}}, {"op" : "Var", "id" : "msg_9_16_434312", "type" : {"op" : "String"}}]}},
"export_as" : ["tmp"]}],
"body" : {"op" : "Var", "id" : "tmp4448", "type" : {"op" : "Data", "type_tag" : "Result1949", "constructors" : [{"tag" : "Error1967", "fields" : [{"op" : "Top"}, {"op" : "String"}]}, {"tag" : "Success1972", "fields" : [{"op" : "Top"}]}]}}}}}]},
"export_as" : ["Exception_7_14_41"]}],
"body" : {"op" : "Let",
"definitions" : [{"name" : {"id" : "v_r_3155_13_20_474307", "type" : {"op" : "String"}},
"value" : {"op" : "App", "fn" : {"op" : "Var", "id" : "charAt2475", "type" : {"op" : "Function", "params" : [{"op" : "String"},
{"op" : "Int"},
{"op" : "Codata", "interface_tag" : "Exception532", "methods" : [{"tag" : "raise602", "params" : [{"op" : "Top"}, {"op" : "String"}], "return" : {"op" : "Bottom"}}]}], "return" : {"op" : "String"}, "purity" : "Effectful"}}, "args" : [{"op" : "Var", "id" : "v_r_2896_304257", "type" : {"op" : "String"}}, {"op" : "Var", "id" : "index_7_344292", "type" : {"op" : "Int"}}, {"op" : "Var", "id" : "Exception_7_14_414297", "type" : {"op" : "Codata", "interface_tag" : "Exception532", "methods" : [{"tag" : "raise602", "params" : [{"op" : "Top"}, {"op" : "String"}], "return" : {"op" : "Bottom"}}]}}]},
"export_as" : ["v_r_3155_13_20_47"]}],
"body" : {"op" : "Let",
"definitions" : [{"name" : {"id" : "tmp4449", "type" : {"op" : "Data", "type_tag" : "Result1949", "constructors" : [{"tag" : "Error1967", "fields" : [{"op" : "Top"}, {"op" : "String"}]}, {"tag" : "Success1972", "fields" : [{"op" : "Top"}]}]}},
"value" : {"op" : "The",
"type" : {"op" : "Data", "type_tag" : "Result1949", "constructors" : [{"tag" : "Error1967", "fields" : [{"op" : "Top"}, {"op" : "String"}]}, {"tag" : "Success1972", "fields" : [{"op" : "Top"}]}]},
"term" : {"op" : "Construct", "type_tag" : "Result1949", "tag" : "Success1972", "args" : [{"op" : "Var", "id" : "v_r_3155_13_20_474307", "type" : {"op" : "String"}}]}},
"export_as" : ["tmp"]}],
"body" : {"op" : "Var", "id" : "tmp4449", "type" : {"op" : "Data", "type_tag" : "Result1949", "constructors" : [{"tag" : "Error1967", "fields" : [{"op" : "Top"}, {"op" : "String"}]}, {"tag" : "Success1972", "fields" : [{"op" : "Top"}]}]}}}}},
"return" : {"params" : [{"id" : "v_tmp_44854508", "type" : {"op" : "Data", "type_tag" : "Result1949", "constructors" : [{"tag" : "Error1967", "fields" : [{"op" : "Top"}, {"op" : "String"}]}, {"tag" : "Success1972", "fields" : [{"op" : "Top"}]}]}}],
"body" : {"op" : "Var", "id" : "v_tmp_44854508", "type" : {"op" : "Data", "type_tag" : "Result1949", "constructors" : [{"tag" : "Error1967", "fields" : [{"op" : "Top"}, {"op" : "String"}]}, {"tag" : "Success1972", "fields" : [{"op" : "Top"}]}]}}}}},
"export_as" : ["v_r_2979_22_49"]}],
"body" : {"op" : "Match",
"scrutinee" : {"op" : "Var", "id" : "v_r_2979_22_494294", "type" : {"op" : "Data", "type_tag" : "Result1949", "constructors" : [{"tag" : "Error1967", "fields" : [{"op" : "Top"}, {"op" : "String"}]}, {"tag" : "Success1972", "fields" : [{"op" : "Top"}]}]}},
"type_tag" : "Result1949",
"clauses" : [{"tag" : "Success1972",
"params" : [{"id" : "v_y_2985_36_634327", "type" : {"op" : "String"}}],
"body" : {"op" : "Let",
"definitions" : [{"name" : {"id" : "tmp4450", "type" : {"op" : "Bool"}},
"value" : {"op" : "App", "fn" : {"op" : "Var", "id" : "infixGte2466", "type" : {"op" : "Function", "params" : [{"op" : "String"},
{"op" : "String"}], "return" : {"op" : "Bool"}, "purity" : "Effectful"}}, "args" : [{"op" : "Var", "id" : "v_y_2985_36_634327", "type" : {"op" : "String"}}, {"op" : "Literal", "type" : {"op" : "String"}, "value" : "0"}]},
"export_as" : ["tmp"]}],
"body" : {"op" : "IfZero",
"cond" : {"op" : "Var", "id" : "tmp4450", "type" : {"op" : "Bool"}},
"then" : {"op" : "Shift",
"label" : {"op" : "Var", "id" : "p_8_94236", "type" : {"op" : "Label"}},
"n" : {"op" : "Literal", "type" : {"op" : "Int"}, "value" : 0},
"k" : {"id" : "k_13_14_44509", "type" : {"op" : "Stack", "resume_return" : {"op" : "Int"}, "resume_args" : [{"op" : "Bottom"}]}},
"returnType" : {"op" : "Int"},
"body" : {"op" : "Literal", "type" : {"op" : "Int"}, "value" : 5}},
"else" : {"op" : "Let",
"definitions" : [{"name" : {"id" : "tmp4451", "type" : {"op" : "Bool"}},
"value" : {"op" : "App", "fn" : {"op" : "Var", "id" : "infixLte2460", "type" : {"op" : "Function", "params" : [{"op" : "String"},
{"op" : "String"}], "return" : {"op" : "Bool"}, "purity" : "Effectful"}}, "args" : [{"op" : "Var", "id" : "v_y_2985_36_634327", "type" : {"op" : "String"}}, {"op" : "Literal", "type" : {"op" : "String"}, "value" : "9"}]},
"export_as" : ["tmp"]}],
"body" : {"op" : "IfZero",
"cond" : {"op" : "Var", "id" : "tmp4451", "type" : {"op" : "Bool"}},
"then" : {"op" : "Shift",
"label" : {"op" : "Var", "id" : "p_8_94236", "type" : {"op" : "Label"}},
"n" : {"op" : "Literal", "type" : {"op" : "Int"}, "value" : 0},
"k" : {"id" : "k_13_14_44510", "type" : {"op" : "Stack", "resume_return" : {"op" : "Int"}, "resume_args" : [{"op" : "Bottom"}]}},
"returnType" : {"op" : "Int"},
"body" : {"op" : "Literal", "type" : {"op" : "Int"}, "value" : 5}},
"else" : {"op" : "Let",
"definitions" : [{"name" : {"id" : "tmp4452", "type" : {"op" : "Int"}},
"value" : {"op" : "App", "fn" : {"op" : "Var", "id" : "infixAdd96", "type" : {"op" : "Function", "params" : [{"op" : "Int"},
{"op" : "Int"}], "return" : {"op" : "Int"}, "purity" : "Effectful"}}, "args" : [{"op" : "Var", "id" : "index_7_344292", "type" : {"op" : "Int"}}, {"op" : "Literal", "type" : {"op" : "Int"}, "value" : 1}]},
"export_as" : ["tmp"]}],
"body" : {"op" : "Let",
"definitions" : [{"name" : {"id" : "tmp4453", "type" : {"op" : "Int"}},
"value" : {"op" : "App", "fn" : {"op" : "Var", "id" : "infixMul99", "type" : {"op" : "Function", "params" : [{"op" : "Int"},
{"op" : "Int"}], "return" : {"op" : "Int"}, "purity" : "Effectful"}}, "args" : [{"op" : "Literal", "type" : {"op" : "Int"}, "value" : 10}, {"op" : "Var", "id" : "acc_8_354252", "type" : {"op" : "Int"}}]},
"export_as" : ["tmp"]}],
"body" : {"op" : "Let",
"definitions" : [{"name" : {"id" : "tmp4454", "type" : {"op" : "Int"}},
"value" : {"op" : "App", "fn" : {"op" : "Var", "id" : "toInt2452", "type" : {"op" : "Function", "params" : [{"op" : "String"}], "return" : {"op" : "Int"}, "purity" : "Effectful"}}, "args" : [{"op" : "Var", "id" : "v_y_2985_36_634327", "type" : {"op" : "String"}}]},
"export_as" : ["tmp"]}],
"body" : {"op" : "Let",
"definitions" : [{"name" : {"id" : "tmp4455", "type" : {"op" : "Int"}},
"value" : {"op" : "App", "fn" : {"op" : "Var", "id" : "infixSub105", "type" : {"op" : "Function", "params" : [{"op" : "Int"},
{"op" : "Int"}], "return" : {"op" : "Int"}, "purity" : "Effectful"}}, "args" : [{"op" : "Var", "id" : "tmp4454", "type" : {"op" : "Int"}}, {"op" : "Var", "id" : "tmp4447", "type" : {"op" : "Int"}}]},
"export_as" : ["tmp"]}],
"body" : {"op" : "Let",
"definitions" : [{"name" : {"id" : "tmp4456", "type" : {"op" : "Int"}},
"value" : {"op" : "App", "fn" : {"op" : "Var", "id" : "infixAdd96", "type" : {"op" : "Function", "params" : [{"op" : "Int"},
{"op" : "Int"}], "return" : {"op" : "Int"}, "purity" : "Effectful"}}, "args" : [{"op" : "Var", "id" : "tmp4453", "type" : {"op" : "Int"}}, {"op" : "Var", "id" : "tmp4455", "type" : {"op" : "Int"}}]},
"export_as" : ["tmp"]}],
"body" : {"op" : "App", "fn" : {"op" : "Var", "id" : "go_6_334326", "type" : {"op" : "Function", "params" : [{"op" : "Int"},
{"op" : "Int"}], "return" : {"op" : "Int"}, "purity" : "Effectful"}}, "args" : [{"op" : "Var", "id" : "tmp4452", "type" : {"op" : "Int"}}, {"op" : "Var", "id" : "tmp4456", "type" : {"op" : "Int"}}]}}}}}}}}}}},
{"tag" : "Error1967",
"params" : [{"id" : "v_y_2986_50_774511", "type" : {"op" : "Data", "type_tag" : "OutOfBounds541", "constructors" : [{"tag" : "OutOfBounds604", "fields" : []}]}}, {"id" : "v_y_2987_51_784512", "type" : {"op" : "String"}}],
"body" : {"op" : "Var", "id" : "acc_8_354252", "type" : {"op" : "Int"}}}],
"default_clause" : {"params" : [],
"body" : {"op" : "Primitive",
"name" : "non-exhaustive match",
"args" : [],
"returns" : [{"id" : "%bottom", "type" : {"op" : "Bottom"}}],
"rest" : {"op" : "Var", "id" : "%bottom", "type" : {"op" : "Bottom"}}}}}}},
"export_as" : ["go_6_33"]}],
"body" : {"op" : "LetRec",
"definitions" : [{"name" : {"id" : "Exception_9_67_944253", "type" : {"op" : "Codata", "interface_tag" : "Exception532", "methods" : [{"tag" : "raise602", "params" : [{"op" : "Top"}, {"op" : "String"}], "return" : {"op" : "Bottom"}}]}},
"value" : {"op" : "New",
"ifce_tag" : "Exception532_Data(OutOfBounds,List())",
"methods" : [{"tag" : "raise602",
"params" : [{"id" : "exception_10_68_954513", "type" : {"op" : "Data", "type_tag" : "OutOfBounds541", "constructors" : [{"tag" : "OutOfBounds604", "fields" : []}]}}, {"id" : "msg_11_69_964514", "type" : {"op" : "String"}}],
"body" : {"op" : "Shift",
"label" : {"op" : "Var", "id" : "p_8_94236", "type" : {"op" : "Label"}},
"n" : {"op" : "Literal", "type" : {"op" : "Int"}, "value" : 0},
"k" : {"id" : "k_13_14_44515", "type" : {"op" : "Stack", "resume_return" : {"op" : "Int"}, "resume_args" : [{"op" : "Bottom"}]}},
"returnType" : {"op" : "Int"},
"body" : {"op" : "Literal", "type" : {"op" : "Int"}, "value" : 5}}}]},
"export_as" : ["Exception_9_67_94"]}],
"body" : {"op" : "Let",
"definitions" : [{"name" : {"id" : "v_r_2992_3_73_1004330", "type" : {"op" : "String"}},
"value" : {"op" : "App", "fn" : {"op" : "Var", "id" : "charAt2475", "type" : {"op" : "Function", "params" : [{"op" : "String"},
{"op" : "Int"},
{"op" : "Codata", "interface_tag" : "Exception532", "methods" : [{"tag" : "raise602", "params" : [{"op" : "Top"}, {"op" : "String"}], "return" : {"op" : "Bottom"}}]}], "return" : {"op" : "String"}, "purity" : "Effectful"}}, "args" : [{"op" : "Var", "id" : "v_r_2896_304257", "type" : {"op" : "String"}}, {"op" : "Literal", "type" : {"op" : "Int"}, "value" : 0}, {"op" : "Var", "id" : "Exception_9_67_944253", "type" : {"op" : "Codata", "interface_tag" : "Exception532", "methods" : [{"tag" : "raise602", "params" : [{"op" : "Top"}, {"op" : "String"}], "return" : {"op" : "Bottom"}}]}}]},
"export_as" : ["v_r_2992_3_73_100"]}],
"body" : {"op" : "Let",
"definitions" : [{"name" : {"id" : "tmp4457", "type" : {"op" : "Bool"}},
"value" : {"op" : "App", "fn" : {"op" : "Var", "id" : "infixEq78", "type" : {"op" : "Function", "params" : [{"op" : "String"},
{"op" : "String"}], "return" : {"op" : "Bool"}, "purity" : "Effectful"}}, "args" : [{"op" : "Var", "id" : "v_r_2992_3_73_1004330", "type" : {"op" : "String"}}, {"op" : "Literal", "type" : {"op" : "String"}, "value" : "-"}]},
"export_as" : ["tmp"]}],
"body" : {"op" : "IfZero",
"cond" : {"op" : "Var", "id" : "tmp4457", "type" : {"op" : "Bool"}},
"then" : {"op" : "App", "fn" : {"op" : "Var", "id" : "go_6_334326", "type" : {"op" : "Function", "params" : [{"op" : "Int"},
{"op" : "Int"}], "return" : {"op" : "Int"}, "purity" : "Effectful"}}, "args" : [{"op" : "Literal", "type" : {"op" : "Int"}, "value" : 0}, {"op" : "Literal", "type" : {"op" : "Int"}, "value" : 0}]},
"else" : {"op" : "Let",
"definitions" : [{"name" : {"id" : "v_r_2993_1_9_79_1064286", "type" : {"op" : "Int"}},
"value" : {"op" : "App", "fn" : {"op" : "Var", "id" : "go_6_334326", "type" : {"op" : "Function", "params" : [{"op" : "Int"},
{"op" : "Int"}], "return" : {"op" : "Int"}, "purity" : "Effectful"}}, "args" : [{"op" : "Literal", "type" : {"op" : "Int"}, "value" : 1}, {"op" : "Literal", "type" : {"op" : "Int"}, "value" : 0}]},
"export_as" : ["v_r_2993_1_9_79_106"]}],
"body" : {"op" : "Let",
"definitions" : [{"name" : {"id" : "tmp4458", "type" : {"op" : "Int"}},
"value" : {"op" : "App", "fn" : {"op" : "Var", "id" : "infixSub105", "type" : {"op" : "Function", "params" : [{"op" : "Int"},
{"op" : "Int"}], "return" : {"op" : "Int"}, "purity" : "Effectful"}}, "args" : [{"op" : "Literal", "type" : {"op" : "Int"}, "value" : 0}, {"op" : "Var", "id" : "v_r_2993_1_9_79_1064286", "type" : {"op" : "Int"}}]},
"export_as" : ["tmp"]}],
"body" : {"op" : "Var", "id" : "tmp4458", "type" : {"op" : "Int"}}}}}}}}}}}}}}}}},
"return" : {"params" : [{"id" : "v_tmp_44834516", "type" : {"op" : "Int"}}],
"body" : {"op" : "Var", "id" : "v_tmp_44834516", "type" : {"op" : "Int"}}}}},
"export_as" : ["n"]}],
"body" : {"op" : "Let",
"definitions" : [{"name" : {"id" : "r2831", "type" : {"op" : "Int"}},
"value" : {"op" : "Reset",
"label" : {"op" : "FreshLabel"},
"region" : {"id" : "b_tmp_44874517", "type" : {"op" : "Ptr"}},
"body" : {"op" : "LetRef",
"ref" : {"id" : "s_34372", "type" : {"op" : "Ref", "to" : {"op" : "Int"}}},
"region" : {"op" : "Var", "id" : "b_tmp_44874517", "type" : {"op" : "Ptr"}},
"binding" : {"op" : "Var", "id" : "n2830", "type" : {"op" : "Int"}},
"body" : {"op" : "LetRec",
"definitions" : [{"name" : {"id" : "countdown_worker_5_194362", "type" : {"op" : "Function", "params" : [], "return" : {"op" : "Int"}, "purity" : "Effectful"}},
"value" : {"op" : "Abs",
"params" : [],
"body" : {"op" : "Let",
"definitions" : [{"name" : {"id" : "i_6_254368", "type" : {"op" : "Int"}},
"value" : {"op" : "Load", "ref" : {"op" : "Var", "id" : "s_34372", "type" : {"op" : "Ref", "to" : {"op" : "Int"}}}},
"export_as" : ["i_6_25"]}],
"body" : {"op" : "Let",
"definitions" : [{"name" : {"id" : "tmp4464", "type" : {"op" : "Bool"}},
"value" : {"op" : "App", "fn" : {"op" : "Var", "id" : "infixEq72", "type" : {"op" : "Function", "params" : [{"op" : "Int"},
{"op" : "Int"}], "return" : {"op" : "Bool"}, "purity" : "Effectful"}}, "args" : [{"op" : "Var", "id" : "i_6_254368", "type" : {"op" : "Int"}}, {"op" : "Literal", "type" : {"op" : "Int"}, "value" : 0}]},
"export_as" : ["tmp"]}],
"body" : {"op" : "IfZero",
"cond" : {"op" : "Var", "id" : "tmp4464", "type" : {"op" : "Bool"}},
"then" : {"op" : "Let",
"definitions" : [{"name" : {"id" : "tmp4459", "type" : {"op" : "Int"}},
"value" : {"op" : "App", "fn" : {"op" : "Var", "id" : "infixSub105", "type" : {"op" : "Function", "params" : [{"op" : "Int"},
{"op" : "Int"}], "return" : {"op" : "Int"}, "purity" : "Effectful"}}, "args" : [{"op" : "Var", "id" : "i_6_254368", "type" : {"op" : "Int"}}, {"op" : "Literal", "type" : {"op" : "Int"}, "value" : 1}]},
"export_as" : ["tmp"]}],
"body" : {"op" : "Let",
"definitions" : [{"name" : {"id" : "__6_324388", "type" : {"op" : "Unit"}},
"value" : {"op" : "Store", "ref" : {"op" : "Var", "id" : "s_34372", "type" : {"op" : "Ref", "to" : {"op" : "Int"}}}, "value" : {"op" : "Var", "id" : "tmp4459", "type" : {"op" : "Int"}}},
"export_as" : ["__6_32"]}],
"body" : {"op" : "App", "fn" : {"op" : "Var", "id" : "countdown_worker_5_194362", "type" : {"op" : "Function", "params" : [], "return" : {"op" : "Int"}, "purity" : "Effectful"}}, "args" : []}}},
"else" : {"op" : "Var", "id" : "i_6_254368", "type" : {"op" : "Int"}}}}}},
"export_as" : ["countdown_worker_5_19"]}],
"body" : {"op" : "App", "fn" : {"op" : "Var", "id" : "countdown_worker_5_194362", "type" : {"op" : "Function", "params" : [], "return" : {"op" : "Int"}, "purity" : "Effectful"}}, "args" : []}}},
"return" : {"params" : [{"id" : "v_tmp_44884518", "type" : {"op" : "Int"}}],
"body" : {"op" : "Var", "id" : "v_tmp_44884518", "type" : {"op" : "Int"}}}},
"export_as" : ["r"]}],
"body" : {"op" : "Let",
"definitions" : [{"name" : {"id" : "tmp4465", "type" : {"op" : "String"}},
"value" : {"op" : "App", "fn" : {"op" : "Var", "id" : "show14", "type" : {"op" : "Function", "params" : [{"op" : "Int"}], "return" : {"op" : "String"}, "purity" : "Effectful"}}, "args" : [{"op" : "Var", "id" : "r2831", "type" : {"op" : "Int"}}]},
"export_as" : ["tmp"]}],
"body" : {"op" : "Let",
"definitions" : [{"name" : {"id" : "tmp4460", "type" : {"op" : "Unit"}},
"value" : {"op" : "App", "fn" : {"op" : "Var", "id" : "println1", "type" : {"op" : "Function", "params" : [{"op" : "String"}], "return" : {"op" : "Unit"}, "purity" : "Effectful"}}, "args" : [{"op" : "Var", "id" : "tmp4465", "type" : {"op" : "String"}}]},
"export_as" : ["tmp"]}],
"body" : {"op" : "Var", "id" : "tmp4460", "type" : {"op" : "Unit"}}}}}}},
"export_as" : ["main"]}],
"main" : {"op" : "App", "fn" : {"op" : "Var", "id" : "main2821", "type" : {"op" : "Function", "params" : [], "return" : {"op" : "Unit"}, "purity" : "Effectful"}}, "args" : []}}